Workbook

Sheet raw_data
A1: Respondent No. | B1: Role | C1: Age_Range | D1: Sex | E1: Education | F1: Years_Managing | G1: Organization_Name | H1: Years_Established | I1: Membership _Size | J1: Farm_Size | K1: Commodity | L1: Value_Adding/ Processed_ Products_Specify | M1: Market | N1: Income_Level | O1: Has_Device | P1: Internet_ Type | Q1: Attended_Training | R1: Training_Details | S1: TB1 | T1: TB2 | U1: TB3 | V1: TB4 | W1: TB5 | X1: TB6 | Y1: OB7 | Z1: OB8 | AA1: OB9 | AB1: OB10 | AC1: OB11 | AD1: OB12 | AE1: EB13 | AF1: EB14 | AG1: EB15 | AH1: DMA16 | AI1: DMA17 | AJ1: DMA18 | AK1: DMA19 | AL1: Support_ Suggestions | AM1: Challenges
A2: 1 | B2: President | C2: 51 & above | D2: Male | E2: High School Grad | F2: 1-2 yrs | G2: Sampao Small Water Irrigation System Association, Inc. | H2: 1-2 yrs | I2: 11-20 members | J2: 1-2 ha | K2: Fresh Vegetables, Corn | L2: No | M2: Public market, Direct selling, Trader, Online | N2: Above 20,000 | O2: Yes | P2: WiFi | Q2: No | S2: 4 | T2: 5 | U2: 4 | V2: 4 | W2: 4 | X2: 4 | Y2: 5 | Z2: 5 | AA2: 5 | AB2: 3 | AC2: 3 | AD2: 3 | AE2: 4 | AF2: 3 | AG2: 4 | AH2: 3 | AI2: 3 | AJ2: 2 | AK2: 3 | AL2: Training, stable internet connection, tools | AM2: Unstable internet connection, limited manpower for digital marketing
A3: 2 | B3: Treasurer | C3: 41-50 | D3: Female | E3: High School Grad | F3: 1-2 yrs | G3: Sampao Small Water Irrigation System Association, Inc. | H3: 1-2 yrs | I3: 11-20 members | J3: 1-2 ha | K3: Fresh Vegetables, Corn | L3: No | M3: Public market, Direct selling, Trader, Online | N3: Above 20,000 | O3: Yes | P3: WiFi | Q3: No | S3: 5 | T3: 5 | U3: 4 | V3: 4 | W3: 4 | X3: 4 | Y3: 4 | Z3: 4 | AA3: 4 | AB3: 3 | AC3: 4 | AD3: 4 | AE3: 4 | AF3: 3 | AG3: 3 | AH3: 2 | AI3: 3 | AJ3: 2 | AK3: 2 | AL3: Training, stable internet connection, tools | AM3: limited digital skills, Unstable internet connection
A4: 3 | B4: Secretary | C4: 41-50 | D4: Female | E4: High School Level | F4: 1-2 yrs | G4: Pinangomhan Farmers Association | H4: 1-2 yrs | I4: 21-30 members | J4: 1-2 ha | K4: Fresh vegetables, Poultry | L4: No | M4: Public market, Direct selling, Trader, Online | N4: Above 20,000 | O4: Yes | P4: WiFi | Q4: No | S4: 5 | T4: 4 | U4: 5 | V4: 3 | W4: 3 | X4: 5 | Y4: 4 | Z4: 5 | AA4: 4 | AB4: 3 | AC4: 3 | AD4: 3 | AE4: 4 | AF4: 4 | AG4: 4 | AH4: 3 | AI4: 3 | AJ4: 2 | AK4: 3 | AL4: Training, reliable tools/ devices | AM4: limited skills, unstable internet connection
A5: 4 | B5: President | C5: 51 & above | D5: Female | E5: High School Grad | F5: 1-2 yrs | G5: Pinangomhan Farmers Association | H5: 1-2 yrs | I5: 21-30 members | J5: 1-2 ha | K5: Fresh vegetables, Poultry | L5: No | M5: Public market, Direct selling, Trader, Online | N5: Above 20,000 | O5: Yes | P5: WiFi | Q5: No | S5: 5 | T5: 5 | U5: 5 | V5: 4 | W5: 3 | X5: 4 | Y5: 4 | Z5: 4 | AA5: 4 | AB5: 4 | AC5: 3 | AD5: 3 | AE5: 4 | AF5: 3 | AG5: 4 | AH5: 3 | AI5: 2 | AJ5: 2 | AK5: 2 | AL5: Training | AM5: unstable internet connection
A6: 5 | B6: BOD | C6: 41-50 | D6: Male | E6: High School Grad | F6: 3-5 yrs | G6: Culaba Integrated Hilltop Farm | H6: 1-2 yrs | I6: 21-30 members | J6: less than 1 ha | K6: Fresh vegetables | L6: No | M6: Direct selling, Online | N6: less than 5,000 | O6: Yes | P6: Both Mobile & WiFi | Q6: No | S6: 4 | T6: 4 | U6: 4 | V6: 3 | W6: 3 | X6: 4 | Y6: 4 | Z6: 4 | AA6: 4 | AB6: 3 | AC6: 3 | AD6: 3 | AE6: 5 | AF6: 3 | AG6: 3 | AH6: 3 | AI6: 3 | AJ6: 3 | AK6: 3 | AL6: Training and more stable internet connection | AM6: unstable internet connection
A7: 6 | B7: Secretary | C7: 31-40 | D7: Female | E7: High School Grad | F7: 3-5 yrs | G7: Culaba Integrated Hilltop Farm | H7: 1-2 yrs | I7: 21-30 members | J7: less than 1 ha | K7: Fresh vegetables | L7: No | M7: Direct selling, Online | N7: less than 5,000 | O7: Yes | P7: Both Mobile & WiFi | Q7: No | S7: 3 | T7: 3 | U7: 3 | V7: 3 | W7: 3 | X7: 3 | Y7: 4 | Z7: 4 | AA7: 4 | AB7: 3 | AC7: 3 | AD7: 3 | AE7: 5 | AF7: 3 | AG7: 3 | AH7: 3 | AI7: 4 | AJ7: 3 | AK7: 3 | AL7: Training and more stable internet connection | AM7: unstable internet connection
A8: 7 | B8: President | C8: 51 & above | D8: Female | E8: High School Grad | F8: 3-5 yrs | G8: Cabucgayan Farmers Association (CAFA) | H8: 3-5 yrs | I8: 21-30 members | J8: 1-2 ha | K8: Fresh Vegetables, Corn | L8: No | M8: Public market, Direct selling, Trader | N8: 10,001 - 20,000 | O8: Yes | P8: None | Q8: No | S8: 5 | T8: 4 | U8: 5 | V8: 3 | W8: 4 | X8: 5 | Y8: 5 | Z8: 5 | AA8: 5 | AB8: 4 | AC8: 4 | AD8: 4 | AE8: 4 | AF8: 4 | AG8: 4 | AH8: 1 | AI8: 2 | AJ8: 1 | AK8: 1 | AL8: Training, Internet Access | AM8: No internet access, and experience in Digital marketing
A9: 8 | B9: Treasurer | C9: 41-50 | D9: Female | E9: High School Grad | F9: 3-5 yrs | G9: Cabucgayan Farmers Association (CAFA) | H9: 3-5 yrs | I9: 21-30 members | J9: 1-2 ha | K9: Fresh Vegetables, Corn | L9: No | M9: Public market, Direct selling, Trader | N9: 10,001 - 20,001 | O9: Yes | P9: None | Q9: No | S9: 5 | T9: 5 | U9: 5 | V9: 4 | W9: 5 | X9: 5 | Y9: 5 | Z9: 5 | AA9: 5 | AB9: 4 | AC9: 3 | AD9: 4 | AE9: 4 | AF9: 4 | AG9: 4 | AH9: 1 | AI9: 2 | AJ9: 2 | AK9: 1 | AL9: Training, Internet Access | AM9: No internet access, and experience in Digital marketing
A10: 9 | B10: President | C10: 51 & above | D10: Male | E10: College Graduate | F10: 1-2 yrs | G10: Samahan ng mga Manggagawa Para sa Agrikulturang Pangkabuhayan (SMAP) | H10: 1-2 yrs | I10: 11-20 members | J10: 1-2 ha | K10: Fresh Vegetables, Corn | L10: No | M10: Public market, Direct selling, Trader | N10: 5,001 - 10,000 | O10: Yes | P10: WiFi | Q10: No | S10: 5 | T10: 4 | U10: 4 | V10: 4 | W10: 4 | X10: 4 | Y10: 4 | Z10: 4 | AA10: 4 | AB10: 3 | AC10: 4 | AD10: 4 | AE10: 4 | AF10: 3 | AG10: 4 | AH10: 2 | AI10: 2 | AJ10: 2 | AK10: 2 | AL10: Training, internet connection, tools | AM10: limited skills, unstable internet connection
A11: 10 | B11: Secretary | C11: 31-40 | D11: Female | E11: College Level | F11: 1-2 yrs | G11: Samahan ng mga Manggagawa Para sa Agrikulturang Pangkabuhayan (SMAP) | H11: 1-2 yrs | I11: 11-20 members | J11: 1-2 ha | K11: Fresh Vegetables, Corn | L11: No | M11: Public market, Direct selling, Trader | N11: 5,001 - 10,001 | O11: Yes | P11: Mobile data | Q11: No | S11: 4 | T11: 4 | U11: 4 | V11: 4 | W11: 4 | X11: 4 | Y11: 5 | Z11: 5 | AA11: 5 | AB11: 4 | AC11: 3 | AD11: 3 | AE11: 3 | AF11: 3 | AG11: 3 | AH11: 1 | AI11: 2 | AJ11: 1 | AK11: 1 | AL11: Training, internet connection, tools | AM11: limited skills, unstable internet connection
A12: 11 | B12: President | C12: 51 & above | D12: Male | E12: High School Grad | F12: 1-2 yrs | G12: Tucdao-Anas Farmers’ Irrigator’s Association, Inc. | H12: 1-2 yrs | I12: 11-20 members | J12: 1-2 ha | K12: Fresh Vegetables, Corn | L12: No | M12: Public market, Direct selling, Trader | N12: Below 5,000 | O12: Yes | P12: WiFi | Q12: No | S12: 5 | T12: 4 | U12: 4 | V12: 3 | W12: 4 | X12: 4 | Y12: 3 | Z12: 4 | AA12: 4 | AB12: 4 | AC12: 3 | AD12: 3 | AE12: 4 | AF12: 4 | AG12: 4 | AH12: 2 | AI12: 3 | AJ12: 2 | AK12: 2 | AL12: Training, internet connection, tools | AM12: limited skills, unstable internet connection
A13: 12 | B13: Treasurer | C13: 41-50 | D13: Female | E13: High School Grad | F13: 1-2 yrs | G13: Tucdao-Anas Farmers’ Irrigator’s Association, Inc. | H13: 1-2 yrs | I13: 11-20 members | J13: 1-2 ha | K13: Fresh Vegetables, Corn | L13: No | M13: Public market, Direct selling, Trader | N13: Below 5,000 | O13: Yes | P13: WiFi | Q13: No | S13: 5 | T13: 5 | U13: 5 | V13: 4 | W13: 4 | X13: 4 | Y13: 4 | Z13: 5 | AA13: 5 | AB13: 4 | AC13: 3 | AD13: 3 | AE13: 3 | AF13: 3 | AG13: 3 | AH13: 2 | AI13: 3 | AJ13: 2 | AK13: 2 | AL13: Training, internet connection, tools | AM13: limited skills, unstable internet connection
... A23: 22 | B23: Secretary | C23: 41-50 | D23: Female | E23: College Grad | F23: 3-5 yrs | G23: Barangay Aringit Farmers Association | H23: 3-5 yrs | I23: 21-30 members | J23: 1-2 ha | K23: Fresh vegetables, Fruits, Poultry | L23: No | M23: Public market, Kadiwa ng Pangulo, Trader, Institutional buyer, Online | N23: 10,001 - 20,000 | O23: Yes | P23: Mobile data | Q23: No | S23: 5 | T23: 5 | U23: 3 | V23: 4 | W23: 4 | X23: 5 | Y23: 5 | Z23: 5 | AA23: 5 | AB23: 3 | AC23: 3 | AD23: 4 | AE23: 5 | AF23: 4 | AG23: 4 | AH23: 3 | AI23: 4 | AJ23: 3 | AK23: 3 | AL23: Training, Tools/ infrastructure, stable internet connection | AM23: limited skills & digital tools, unstable internet connection
A24: 23 | B24: President | C24: 31-40 | D24: Male | E24: College Level | F24: 1-2 yrs | G24: Julitanhon Integrated Farmers Association | H24: 1-2 yrs | I24: 11-20 members | J24: less than 1 ha | K24: Fresh vegetables, Poultry | L24: No | M24: Public market, Direct selling, Institutional buyer, Online | N24: Above 20,000 | O24: Yes | P24: Mobile data | Q24: Yes | R24: Posting products on social media | S24: 3 | T24: 4 | U24: 3 | V24: 3 | W24: 4 | X24: 5 | Y24: 4 | Z24: 5 | AA24: 5 | AB24: 3 | AC24: 4 | AD24: 4 | AE24: 4 | AF24: 4 | AG24: 4 | AH24: 3 | AI24: 3 | AJ24: 3 | AK24: 2 | AL24: tools/ infrastructure, additional training | AM24: few buyers online
A25: 24 | B25: Treasurer | C25: 31-40 | D25: Male | E25: Elementary Graduate | F25: 1-2 yrs | G25: Julitanhon Integrated Farmers Association | H25: 1-2 yrs | I25: 11-20 members | J25: less than 1 ha | K25: Fresh vegetables, Poultry | L25: No | M25: Public market, Direct selling, Trader, Online | N25: Above 20,000 | O25: Yes | P25: Mobile data | Q25: Yes | R25: Posting products on social media | S25: 3 | T25: 4 | U25: 4 | V25: 3 | W25: 3 | X25: 4 | Y25: 4 | Z25: 4 | AA25: 3 | AB25: 4 | AC25: 4 | AD25: 4 | AE25: 4 | AF25: 4 | AG25: 4 | AH25: 3 | AI25: 2 | AJ25: 3 | AK25: 2 | AL25: tools/ infrastructure, additional training | AM25: few buyers online
A26: 25 | B26: Secretary | C26: 51 & above | D26: Female | E26: High School Level | F26: 3-5 yrs | G26: Pagburublig han Parag-uma Association | H26: 3-5 yrs | I26: more than 30 | J26: 1-2 ha | K26: Fresh vegetables, Poultry, Processed products | L26: Yes; Banana chips, Virgin coconut oil | M26: Public market, Trader,Direct selling, Online | N26: Above 20,000 | O26: Yes | P26: Both Mobile & WiFi | Q26: Yes | R26: Posting products on social media | S26: 4 | T26: 3 | U26: 3 | V26: 3 | W26: 3 | X26: 4 | Y26: 3 | Z26: 4 | AA26: 5 | AB26: 3 | AC26: 4 | AD26: 4 | AE26: 3 | AF26: 4 | AG26: 3 | AH26: 3 | AI26: 4 | AJ26: 3 | AK26: 3 | AL26: Training, Tools/ infrastructure, stable internet connection | AM26: Higher fuel prices impact deliveries for online buyers
A27: 26 | B27: BOD | C27: 51 & above | D27: Female | E27: College Level | F27: 3-5 yrs | G27: Pagburublig han Parag-uma Association | H27: 3-5 yrs | I27: more than 30 | J27: 1-2 ha | K27: Fresh vegetables, Poultry, Processed products | L27: Yes; Banana chips, Virgin coconut oil | M27: Public market, Trader,Direct selling, Online | N27: Above 20,000 | O27: Yes | P27: Both Mobile & WiFi | Q27: Yes | R27: Posting products on social media | S27: 4 | T27: 3 | U27: 4 | V27: 3 | W27: 4 | X27: 4 | Y27: 3 | Z27: 4 | AA27: 3 | AB27: 3 | AC27: 4 | AD27: 4 | AE27: 3 | AF27: 4 | AG27: 4 | AH27: 3 | AI27: 3 | AJ27: 3 | AK27: 3 | AL27: Training, Tools/ infrastructure, stable internet connection | AM27: Higher fuel prices impact deliveries for online buyers
A28: 27 | B28: Secretary | C28: 31-40 | D28: Female | E28: College Grad | F28: 3-5 yrs | G28: Guingauan Small Farmers Association | H28: 3-5 yrs | I28: 11-20 members | J28: less than 1 ha | K28: Fresh vegetables | L28: No | M28: Trader, Direct selling | N28: Below 5,000 | O28: Yes | P28: Both Mobile & WiFi | Q28: No | S28: 4 | T28: 3 | U28: 4 | V28: 3 | W28: 4 | X28: 4 | Y28: 4 | Z28: 4 | AA28: 4 | AB28: 3 | AC28: 4 | AD28: 4 | AE28: 5 | AF28: 4 | AG28: 4 | AH28: 2 | AI28: 3 | AJ28: 3 | AK28: 2 | AL28: Training, Stable internet connection | AM28: Poor photo and writing skills for online marketing.
A29: 28 | B29: Member | C29: 41-50 | D29: Female | E29: High School Level | F29: 1-2 yrs | G29: Guingauan Small Farmers Association | H29: 3-5 y | I29: 11-20 members | J29: less than 1 ha | K29: Fresh vegetables | L29: No | M29: Trader, Direct selling | N29: Below 5,000 | O29: Yes | P29: Mobile data | Q29: No | S29: 5 | T29: 4 | U29: 4 | V29: 3 | W29: 3 | X29: 4 | Y29: 5 | Z29: 5 | AA29: 5 | AB29: 4 | AC29: 5 | AD29: 4 | AE29: 3 | AF29: 4 | AG29: 3 | AH29: 1 | AI29: 2 | AJ29: 1 | AK29: 1 | AL29: Training, Stable internet connection | AM29: Limited skills
A30: 29 | B30: President | C30: 51 & above | D30: Male | E30: Elementary Level | F30: 1-2 yrs | G30: Assuncion Del Senior Integrated Farmers Association | H30: 1-2 yrs | I30: 11-20 members | J30: less than 1 ha | K30: Fresh vegetables | L30: No | M30: Direct selling, Trader | N30: Below 5,000 | O30: Yes | P30: Mobile data | Q30: No | S30: 5 | T30: 5 | U30: 5 | V30: 5 | W30: 5 | X30: 5 | Y30: 5 | Z30: 5 | AA30: 5 | AB30: 3 | AC30: 5 | AD30: 4 | AE30: 4 | AF30: 4 | AG30: 4 | AH30: 1 | AI30: 2 | AJ30: 2 | AK30: 1 | AL30: Tools, internet access, Training | AM30: Lack of tools/devices, and skills
A31: 30 | B31: Treasurer | C31: 51 & above | D31: Female | E31: Elementary Graduate | F31: 1-2 yrs | G31: Assuncion Del Senior Integrated Farmers Association | H31: 1-2 yrs | I31: 11-20 members | J31: less than 1 ha | K31: Fresh vegetables | L31: No | M31: Direct selling, Trader | N31: Below 5,000 | O31: Yes | P31: Mobile data | Q31: No | S31: 5 | T31: 5 | U31: 5 | V31: 4 | W31: 4 | X31: 4 | Y31: 5 | Z31: 5 | AA31: 5 | AB31: 4 | AC31: 5 | AD31: 4 | AE31: 5 | AF31: 4 | AG31: 4 | AH31: 2 | AI31: 2 | AJ31: 2 | AK31: 2 | AL31: Tools, internet access, Training | AM31: Lack of tools/devices, and skills
A32: 31 | B32: Secretary | C32: 51 & above | D32: Female | E32: College Graduate | F32: 3-5 yrs | G32: San Vicente Farmers and Fisherfolks Association | H32: 3-5 yrs | I32: more than 30 | J32: less than 1 ha | K32: Fresh vegetables, Poultry | L32: No | M32: Trader, Direct selling, Online | N32: Above 20,000 | O32: Yes | P32: Both Mobile & WiFi | Q32: No | S32: 3 | T32: 3 | U32: 3 | V32: 3 | W32: 3 | X32: 4 | Y32: 4 | Z32: 4 | AA32: 4 | AB32: 3 | AC32: 3 | AD32: 4 | AE32: 4 | AF32: 4 | AG32: 4 | AH32: 3 | AI32: 4 | AJ32: 3 | AK32: 3 | AL32: Training | AM32: No formal training in digital marketing
A33: 32 | B33: Treasurer | C33: 51 & above | D33: Female | E33: High School Grad | F33: 1-2 yrs | G33: San Vicente Farmers and Fisherfolks Association | H33: 3-5 yrs | I33: more than 30 | J33: less than 1 ha | K33: Fresh vegetables, Poultry | L33: No | M33: Public market, Direct selling, Online | N33: Above 20,000 | O33: Yes | P33: Both Mobile & WiFi | Q33: No | S33: 4 | T33: 4 | U33: 4 | V33: 3 | W33: 3 | X33: 4 | Y33: 5 | Z33: 5 | AA33: 5 | AB33: 3 | AC33: 5 | AD33: 5 | AE33: 5 | AF33: 5 | AG33: 5 | AH33: 3 | AI33: 3 | AJ33: 2 | AK33: 2 | AL33: Training, Stable internet connection, tools | AM33: limited tools, unstable internet connection
A34: 33 | B34: Treasurer | C34: 18-30 | D34: Female | E34: High School Level | F34: less than 1 | G34: Blissful N' Abound Integrated Farmers Association | H34: 1-2 yrs | I34: 11-20 members | J34: less than 1 ha | K34: Fresh vegetables, Poultry | L34: No | M34: Public market, Direct selling, Online | N34: Above 20,000 | O34: Yes | P34: WiFi | Q34: No | S34: 3 | T34: 3 | U34: 4 | V34: 4 | W34: 4 | X34: 4 | Y34: 5 | Z34: 5 | AA34: 5 | AB34: 3 | AC34: 3 | AD34: 3 | AE34: 4 | AF34: 4 | AG34: 4 | AH34: 3 | AI34: 3 | AJ34: 3 | AK34: 2 | AL34: Training | AM34: Lack of digital marketing and content creation skills.
A35: 34 | B35: Business Manager | C35: 31-40 | D35: Male | E35: High School Grad | F35: less than 1 | G35: Blissful N' Abound Integrated Farmers Association | H35: 1-2 yrs | I35: 11-20 members | J35: less than 1 ha | K35: Fresh vegetables, Poultry | L35: No | M35: Public market, Direct selling, Online | N35: Above 20,000 | O35: Yes | P35: WiFi | Q35: No | S35: 4 | T35: 4 | U35: 3 | V35: 5 | W35: 5 | X35: 4 | Y35: 5 | Z35: 5 | AA35: 5 | AB35: 3 | AC35: 3 | AD35: 3 | AE35: 4 | AF35: 4 | AG35: 4 | AH35: 2 | AI35: 3 | AJ35: 3 | AK35: 2 | AL35: Training | AM35: Lack of basic digital skills.
A36: 35 | B36: President | C36: 41-50 | D36: Male | E36: College Graduate | F36: 1-2 yrs | G36: District 4 Rice, Coconut and Banana Farmers Association | H36: 1-2 yrs | I36: 21-30 members | J36: less than 1 ha | K36: Fresh vegetables, Poultry | L36: No | M36: Trader, Direct, Institutional buyer | N36: Above 20,000 | O36: Yes | P36: Mobile data | Q36: No | S36: 4 | T36: 4 | U36: 4 | V36: 3 | W36: 4 | X36: 4 | Y36: 4 | Z36: 4 | AA36: 4 | AB36: 3 | AC36: 4 | AD36: 4 | AE36: 4 | AF36: 4 | AG36: 4 | AH36: 1 | AI36: 2 | AJ36: 2 | AK36: 1 | AL36: Training, Stable internet connection, tools | AM36: Not using digital marketing yet.
A37: 36 | B37: Business Manager | C37: 41-50 | D37: Female | E37: High School Level | F37: 1-2 yrs | G37: District 4 Rice, Coconut and Banana Farmers Association | H37: 1-2 yrs | I37: 21-30 members | J37: less than 1 ha | K37: Fresh vegetables, Poultry | L37: No | M37: Trader, Direct, Institutional buyer | N37: Above 20,000 | O37: Yes | P37: Mobile data | Q37: No | S37: 4 | T37: 5 | U37: 5 | V37: 4 | W37: 4 | X37: 5 | Y37: 4 | Z37: 4 | AA37: 5 | AB37: 3 | AC37: 4 | AD37: 4 | AE37: 4 | AF37: 4 | AG37: 4 | AH37: 2 | AI37: 3 | AJ37: 2 | AK37: 1 | AL37: Training, Stable internet connection, tools | AM37: Not using digital marketing yet.
A38: 37 | B38: Treasurer | C38: 41-50 | D38: Female | E38: High School Grad | F38: 3-5 yrs | G38: Lamaca Farmers Association | H38: 3-5 yrs | I38: 21-30 members | J38: 1-2 ha | K38: Fresh vegetables, Poultry | L38: No | M38: Public market, Direct selling | N38: Above 20,000 | O38: Yes | P38: Both Mobile & WiFi | Q38: No | S38: 4 | T38: 4 | U38: 4 | V38: 3 | W38: 3 | X38: 3 | Y38: 3 | Z38: 4 | AA38: 4 | AB38: 3 | AC38: 4 | AD38: 4 | AE38: 3 | AF38: 4 | AG38: 4 | AH38: 2 | AI38: 3 | AJ38: 2 | AK38: 2 | AL38: Training, tools | AM38: unstable internet connection
A39: 38 | B39: Secretary | C39: 41-50 | D39: Female | E39: College Grad | F39: 3-5 yrs | G39: Lamaca Farmers Association | H39: 3-5 yrs | I39: 21-30 members | J39: 1-2 ha | K39: Fresh vegetables, Poultry | L39: No | M39: Public market, Direct selling | N39: Above 20,000 | O39: Yes | P39: Both Mobile & WiFi | Q39: No | S39: 4 | T39: 3 | U39: 3 | V39: 3 | W39: 3 | X39: 3 | Y39: 4 | Z39: 4 | AA39: 4 | AB39: 4 | AC39: 3 | AD39: 3 | AE39: 3 | AF39: 3 | AG39: 3 | AH39: 2 | AI39: 3 | AJ39: 2 | AK39: 2 | AL39: Training, stable internet connection | AM39: Limited skills, time, budget, and manpower, lack of strategy
... A41: 40 | B41: Treasurer | C41: 41-50 | D41: Female | E41: College Level | F41: 3-5 yrs | G41: San Roque Farmers and Fisherfolks Association | H41: 3-5 yrs | I41: 21-30 members | J41: less than 1 ha | K41: Poultry | L41: No | M41: Trader, Direct selling | N41: Above 20,000 | O41: Yes | P41: Both Mobile & WiFi | Q41: No | S41: 4 | T41: 3 | U41: 3 | V41: 4 | W41: 4 | X41: 4 | Y41: 4 | Z41: 4 | AA41: 3 | AB41: 3 | AC41: 5 | AD41: 3 | AE41: 3 | AF41: 3 | AG41: 3 | AH41: 1 | AI41: 2 | AJ41: 1 | AK41: 1 | AL41: Training, stable internet connection | AM41: Not using digital marketing yet.
A42: 41 | B42: Treasurer | C42: 31-40 | D42: Female | E42: High School Grad | F42: 3-5 yrs | G42: Calintaan Farmers Association | H42: 3-5 yrs | I42: 21-30 members | J42: less than 1 ha | K42: Poultry | L42: No | M42: Trader, Direct Selling, Institutional buyer | N42: Above 20,000 | O42: Yes | P42: Mobile data | Q42: Yes | R42: Posting products on social media | S42: 5 | T42: 4 | U42: 4 | V42: 3 | W42: 3 | X42: 4 | Y42: 4 | Z42: 3 | AA42: 4 | AB42: 4 | AC42: 3 | AD42: 3 | AE42: 3 | AF42: 3 | AG42: 3 | AH42: 2 | AI42: 4 | AJ42: 2 | AK42: 2 | AL42: stable internet connection, additional Training | AM42: unstable internet connection
A43: 42 | B43: Secretary | C43: 31-40 | D43: Female | E43: High School Grad | F43: 3-5 yrs | G43: Calintaan Farmers Association | H43: 3-5 ys | I43: 21-30 members | J43: less than 1 ha | K43: Poultry | L43: No | M43: Trader, Direct Selling, Institutional buyer | N43: Above 20,000 | O43: Yes | P43: Mobile data | Q43: Yes | R43: Posting products on social media | S43: 5 | T43: 4 | U43: 4 | V43: 3 | W43: 4 | X43: 4 | Y43: 4 | Z43: 4 | AA43: 4 | AB43: 3 | AC43: 3 | AD43: 3 | AE43: 3 | AF43: 3 | AG43: 3 | AH43: 3 | AI43: 4 | AJ43: 3 | AK43: 3 | AL43: stable internet connection, additional Training | AM43: unstable internet connection
A44: 43 | B44: President | C44: 41-50 | D44: Female | E44: High School Grad | F44: 3-5 yrs | G44: Barangay Dayanog Small Coconut Farmers and Fisherfolks Association | H44: 3-5 yrs | I44: 11-20 members | J44: less than 1 ha | K44: Fresh vegetables | L44: No | M44: Trader, Direct selling | N44: Above 20,000 | O44: Yes | P44: Mobile data | Q44: No | S44: 5 | T44: 5 | U44: 4 | V44: 4 | W44: 4 | X44: 4 | Y44: 5 | Z44: 5 | AA44: 4 | AB44: 3 | AC44: 4 | AD44: 4 | AE44: 4 | AF44: 3 | AG44: 4 | AH44: 1 | AI44: 2 | AJ44: 1 | AK44: 1 | AL44: Training, stable internet connection | AM44: limited digital tools and skills, unstable internet connection
A45: 44 | B45: Secretary | C45: 41-50 | D45: Female | E45: High School Level | F45: 3-5 yrs | G45: Barangay Dayanog Small Coconut Farmers and Fisherfolks Association | H45: 3-5 yrs | I45: 11-20 members | J45: less than 1 ha | K45: Fresh vegetables | L45: No | M45: Trader, Direct selling | N45: Above 20,000 | O45: Yes | P45: Mobile data | Q45: No | S45: 5 | T45: 5 | U45: 4 | V45: 4 | W45: 4 | X45: 5 | Y45: 5 | Z45: 5 | AA45: 5 | AB45: 4 | AC45: 4 | AD45: 4 | AE45: 5 | AF45: 3 | AG45: 4 | AH45: 1 | AI45: 2 | AJ45: 1 | AK45: 1 | AL45: Training, stable internet connection | AM45: limited digital tools and skills, unstable internet connection
A46: 45 | B46: President | C46: 41-50 | D46: Male | E46: High School Graduate | F46: 1-2 yrs | G46: PUNDOK MAAMUMAHON | H46: 1-2 yrs | I46: more than 30 | J46: 1-2 ha | K46: Fresh vegetables, Poultry | L46: No | M46: Public market, Trader,Direct selling | N46: Above 20,000 | O46: Yes | P46: Both Mobile & WiFi | Q46: No | S46: 4 | T46: 3 | U46: 3 | V46: 3 | W46: 3 | X46: 4 | Y46: 4 | Z46: 4 | AA46: 4 | AB46: 3 | AC46: 4 | AD46: 3 | AE46: 4 | AF46: 3 | AG46: 4 | AH46: 1 | AI46: 3 | AJ46: 2 | AK46: 1 | AL46: Training | AM46: Limited skills and manpower
A47: 46 | B47: Member | C47: 41-50 | D47: Male | E47: College Graduate | F47: 1-2 yrs | G47: PUNDOK MAAMUMAHON | H47: 1-2 yrs | I47: more than 30 | J47: 1-2 ha | K47: Fresh vegetables, Poultry | L47: No | M47: Public market, Trader,Direct selling | N47: Above 20,000 | O47: Yes | P47: Both Mobile & WiFi | Q47: No | S47: 3 | T47: 3 | U47: 3 | V47: 3 | W47: 3 | X47: 4 | Y47: 4 | Z47: 4 | AA47: 4 | AB47: 3 | AC47: 3 | AD47: 3 | AE47: 4 | AF47: 4 | AG47: 4 | AH47: 2 | AI47: 4 | AJ47: 3 | AK47: 2 | AL47: Training | AM47: Limited time and skills for creating content
A48: 47 | B48: President | C48: 51 & above | D48: Male | E48: High School Level | F48: 1-2 yrs | G48: Coot-Dinahugan Integrated Farming Association | H48: 1-2 yrs | I48: 21-30 members | J48: less than 1 ha | K48: Livestock | L48: No | M48: Trader, Direct selling | N48: Above 20,000 | O48: Yes | P48: Mobile data | Q48: No | S48: 5 | T48: 5 | U48: 5 | V48: 4 | W48: 4 | X48: 5 | Y48: 4 | Z48: 5 | AA48: 5 | AB48: 3 | AC48: 4 | AD48: 3 | AE48: 4 | AF48: 3 | AG48: 4 | AH48: 1 | AI48: 1 | AJ48: 1 | AK48: 1 | AL48: Training, tools, stable internet connection | AM48: limited tools/ devices and internet access
A49: 48 | B49: Secretary | C49: 41-50 | D49: Female | E49: High school Graduate | F49: 1-2 yrs | G49: Coot-Dinahugan Integrated Farming Association | H49: 1-2 yrs | I49: 21-30 members | J49: less than 1 ha | K49: Livestock | L49: No | M49: Trader, Direct selling | N49: Above 20,000 | O49: Yes | P49: Mobile data | Q49: No | S49: 5 | T49: 4 | U49: 4 | V49: 4 | W49: 4 | X49: 5 | Y49: 4 | Z49: 5 | AA49: 4 | AB49: 3 | AC49: 4 | AD49: 3 | AE49: 4 | AF49: 3 | AG49: 3 | AH49: 1 | AI49: 1 | AJ49: 1 | AK49: 1 | AL49: Training, tools, stable internet connection | AM49: limited tools/ devices and internet access
A50: 49 | B50: Business Manager | C50: 41-50 | D50: Male | E50: College Graduate | F50: 3-5 yrs | G50: Magallanes Farmers Association | H50: 3-5 yrs | I50: 11-20 members | J50: less than 1 ha | K50: Livestock, Poultry | L50: No | M50: Direct selling, Institutional buyer | N50: Above 20,000 | O50: Yes | P50: Both Mobile & WiFi | Q50: No | S50: 4 | T50: 4 | U50: 4 | V50: 3 | W50: 3 | X50: 3 | Y50: 4 | Z50: 3 | AA50: 4 | AB50: 3 | AC50: 3 | AD50: 3 | AE50: 4 | AF50: 4 | AG50: 4 | AH50: 2 | AI50: 3 | AJ50: 2 | AK50: 2 | AL50: Training | AM50: limited skills
A51: 50 | B51: President | C51: 51 & above | D51: Male | E51: College level | F51: 3-5 yrs | G51: Magallanes Farmers Association | H51: 3-5 yrs | I51: 11-20 members | J51: less than 1 ha | K51: Livestock, Poultry | L51: No | M51: Direct selling, Institutional buyer, online | N51: Above 20,000 | O51: Yes | P51: Both Mobile & WiFi | Q51: No | S51: 5 | T51: 4 | U51: 3 | V51: 3 | W51: 4 | X51: 4 | Y51: 3 | Z51: 3 | AA51: 5 | AB51: 4 | AC51: 3 | AD51: 3 | AE51: 3 | AF51: 4 | AG51: 3 | AH51: 3 | AI51: 3 | AJ51: 3 | AK51: 3 | AL51: Training, stable internet connection | AM51: limited skills and tools
A52: 51 | B52: President | C52: 51 & above | D52: Female | E52: College Graduate | F52: 3-5 yrs | G52: Pinamudlan Women's Association | H52: 3-5 yrs | I52: 11-20 members | J52: less than 1 ha | K52: livestock | L52: No | M52: Institutional buyer, direct selling | N52: Above 20,000 | O52: Oo | P52: Mobile data | Q52: Yes | R52: Posting products on social media | S52: 5 | T52: 4 | U52: 5 | V52: 4 | W52: 4 | X52: 4 | Y52: 4 | Z52: 4 | AA52: 4 | AB52: 4 | AC52: 4 | AD52: 4 | AE52: 3 | AF52: 3 | AG52: 3 | AH52: 2 | AI52: 2 | AJ52: 2 | AK52: 2 | AL52: Tools/devices, stable internet connection | AM52: unstable internet connection
A53: 52 | B53: Secretary | C53: 41-50 | D53: Female | E53: High School level | F53: 3-5 yrs | G53: Pinamudlan Women's Association | H53: 3-5 yrs | I53: 11-20 members | J53: less than 1 ha | K53: livestock | L53: No | M53: Institutional buyer, direct selling | N53: Above 20,000 | O53: Oo | P53: Mobile data | Q53: Yes | R53: Posting products on social media | S53: 5 | T53: 4 | U53: 4 | V53: 4 | W53: 4 | X53: 4 | Y53: 5 | Z53: 5 | AA53: 5 | AB53: 4 | AC53: 4 | AD53: 4 | AE53: 3 | AF53: 3 | AG53: 3 | AH53: 2 | AI53: 3 | AJ53: 2 | AK53: 2 | AL53: Tools/devices, stable internet connection | AM53: unstable internet connection
A54: 53 | B54: President | C54: 51 & above | D54: Female | E54: High School Grad | F54: 3-5 yrs | G54: Maalagaron Abtik Responsable Ug Ehemplo Nga Mga Kababayen-An (MARE) CARES sa Hinapo Women’s Association | H54: 3-5 yrs | I54: 11-20 members | J54: less than 1 ha | K54: Poultry | L54: No | M54: Trader, Direct selling | N54: Above 20,000 | O54: Oo | P54: WiFi | Q54: No | S54: 4 | T54: 4 | U54: 4 | V54: 4 | W54: 4 | X54: 5 | Y54: 5 | Z54: 5 | AA54: 5 | AB54: 3 | AC54: 3 | AD54: 3 | AE54: 4 | AF54: 4 | AG54: 4 | AH54: 2 | AI54: 3 | AJ54: 2 | AK54: 2 | AL54: training, tools/devices, stable internet connection | AM54: lack of skills/experience, budget, tools, and stable internet connection
A55: 54 | B55: Business Manager | C55: 41-50 | D55: Female | E55: High School Grad | F55: 3-5 yrs | G55: Maalagaron Abtik Responsable Ug Ehemplo Nga Mga Kababayen-An (MARE) CARES sa Hinapo Women’s Association | H55: 3-5 yrs | I55: 11-20 members | J55: less than 1 ha | K55: Poultry | L55: No | M55: Trader, Direct selling | N55: Above 20,000 | O55: Oo | P55: WiFi | Q55: No | S55: 5 | T55: 4 | U55: 4 | V55: 4 | W55: 4 | X55: 4 | Y55: 4 | Z55: 5 | AA55: 4 | AB55: 4 | AC55: 3 | AD55: 3 | AE55: 4 | AF55: 3 | AG55: 4 | AH55: 1 | AI55: 4 | AJ55: 2 | AK55: 1 | AL55: training, tools/devices, stable internet connection | AM55: lack of skills/experience, budget, tools, and stable internet connection
A56: 55 | B56: President | C56: 41-50 | D56: Male | E56: College Graduate | F56: 1-2 yrs | G56: Cabulisan Farmers Association | H56: 1-2 yrs | I56: 21-30 members | J56: less than 1 ha | K56: Poultry | L56: No | M56: Trader, Direct selling, Institutional buyer | N56: Above 20,000 | O56: Yes | P56: Both Mobile & WiFi | Q56: No | S56: 4 | T56: 3 | U56: 3 | V56: 4 | W56: 4 | X56: 5 | Y56: 4 | Z56: 5 | AA56: 4 | AB56: 3 | AC56: 3 | AD56: 3 | AE56: 4 | AF56: 3 | AG56: 4 | AH56: 2 | AI56: 4 | AJ56: 3 | AK56: 2 | AL56: training, tools | AM56: limited skills in content creation
A57: 56 | B57: Secretary | C57: 31-40 | D57: Female | E57: High School Grad | F57: 1-2 yrs | G57: Cabulisan Farmers Association | H57: 1-2 yrs | I57: 21-30 members | J57: less than 1 ha | K57: Poultry | L57: No | M57: Trader, Direct selling, Institutional buyer | N57: Above 20,000 | O57: Yes | P57: Both Mobile & WiFi | Q57: No | S57: 4 | T57: 4 | U57: 4 | V57: 4 | W57: 5 | X57: 4 | Y57: 4 | Z57: 5 | AA57: 5 | AB57: 3 | AC57: 3 | AD57: 3 | AE57: 4 | AF57: 4 | AG57: 4 | AH57: 1 | AI57: 3 | AJ57: 2 | AK57: 1 | AL57: training, tools | AM57: Limited time and skills for creating content
A58: 57 | B58: President | C58: 51 & above | D58: Female | E58: High School Graduate | F58: 1-2 yrs | G58: Talisay Women's Association | H58: 1-2 yrs | I58: 21-30 members | J58: less than 1 ha | K58: Poultry | L58: No | M58: Trader, Direct selling | N58: Above 20,000 | O58: Yes | P58: Mobile data | Q58: No | S58: 5 | T58: 4 | U58: 5 | V58: 4 | W58: 3 | X58: 5 | Y58: 4 | Z58: 5 | AA58: 4 | AB58: 3 | AC58: 3 | AD58: 3 | AE58: 3 | AF58: 3 | AG58: 4 | AH58: 1 | AI58: 3 | AJ58: 2 | AK58: 1 | AL58: training, tools | AM58: unstable internet connection
A59: 58 | B59: BOD | C59: 51 & above | D59: Female | E59: High School Graduate | F59: 1-2 yrs | G59: Talisay Women's Association | H59: 1-2 yrs | I59: 21-30 members | J59: less than 1 ha | K59: Poultry | L59: No | M59: Trader, Direct selling | N59: Above 20,000 | O59: Yes | P59: Mobile data | Q59: No | S59: 5 | T59: 5 | U59: 5 | V59: 4 | W59: 4 | X59: 4 | Y59: 5 | Z59: 5 | AA59: 5 | AB59: 3 | AC59: 3 | AD59: 3 | AE59: 4 | AF59: 3 | AG59: 4 | AH59: 2 | AI59: 4 | AJ59: 2 | AK59: 2 | AL59: training, stable internet connection | AM59: Unstable internet connection
A60: 59 | B60: President | C60: 31-40 | D60: Male | E60: College Level | F60: 1-2 yrs | G60: Sabang II Rural Improvement Club | H60: 1-2 yrs | I60: 21-30 members | J60: less than 1 ha | K60: Poultry | L60: No | M60: Direct Selling, Institutional buyer | N60: Above 20,000 | O60: Yes | P60: Both Mobile & WiFi | Q60: No | S60: 3 | T60: 4 | U60: 3 | V60: 3 | W60: 3 | X60: 4 | Y60: 3 | Z60: 4 | AA60: 3 | AB60: 2 | AC60: 3 | AD60: 3 | AE60: 3 | AF60: 3 | AG60: 4 | AH60: 3 | AI60: 4 | AJ60: 3 | AK60: 3 | AL60: training | AM60: lack of consistency in creating content
A61: 60 | B61: Treasurer | C61: 31-40 | D61: Female | E61: High School Grad | F61: 1-2 yrs | G61: Sabang II Rural Improvement Club | H61: 1-2 yrs | I61: 21-30 members | J61: less than 1 ha | K61: Poultry | L61: No | M61: Direct Selling, Institutional buyer | N61: Above 20,000 | O61: Yes | P61: Both Mobile & WiFi | Q61: No | S61: 4 | T61: 3 | U61: 3 | V61: 3 | W61: 4 | X61: 4 | Y61: 4 | Z61: 5 | AA61: 4 | AB61: 3 | AC61: 4 | AD61: 3 | AE61: 4 | AF61: 3 | AG61: 4 | AH61: 3 | AI61: 4 | AJ61: 3 | AK61: 3 | AL61: training | AM61: transportation for product delivery
A62: 61 | B62: President | C62: 51 & above | D62: Male | E62: High School Level | F62: 1-2 yrs | G62: Aguada Fisherfolks Mangrove Kinis and Bangus Sustainable Association | H62: 1-2 yrs | I62: 11-20 members | J62: less than 1 ha | K62: Poultry | L62: No | M62: Trader, Direct selling | N62: Above 20,000 | O62: Yes | P62: Both Mobile & WiFi | Q62: No | S62: 4 | T62: 5 | U62: 4 | V62: 4 | W62: 4 | X62: 5 | Y62: 4 | Z62: 5 | AA62: 4 | AB62: 3 | AC62: 4 | AD62: 3 | AE62: 5 | AF62: 4 | AG62: 5 | AH62: 2 | AI62: 3 | AJ62: 2 | AK62: 2 | AL62: Training | AM62: Limited digital skills
A63: 62 | B63: Treasurer | C63: 41-50 | D63: Female | E63: High School Grad | F63: 1-2 yrs | G63: Aguada Fisherfolks Mangrove Kinis and Bangus Sustainable Association | H63: 1-2 yrs | I63: 11-20 members | J63: less than 1 ha | K63: Poultry | L63: No | M63: Trader, Direct selling | N63: Above 20,000 | O63: Yes | P63: Both Mobile & WiFi | Q63: No | S63: 5 | T63: 4 | U63: 4 | V63: 4 | W63: 4 | X63: 4 | Y63: 4 | Z63: 5 | AA63: 5 | AB63: 4 | AC63: 3 | AD63: 3 | AE63: 5 | AF63: 4 | AG63: 5 | AH63: 2 | AI63: 4 | AJ63: 2 | AK63: 2 | AL63: Training | AM63: Limited digital skills
A64: 63 | B64: President | C64: 41-50 | D64: Female | E64: High School Level | F64: 1-2 yrs | G64: Magsasakang Masisipag ng Mapanas (3M) Association | H64: 1-2 yrs | I64: 21-30 members | J64: 1-2 ha | K64: Fresh vegetables, Corn | L64: No | M64: Trader, Direct selling, Online | N64: 10,001 - 20,000 | O64: Yes | P64: Both Mobile & WiFi | Q64: No | S64: 4 | T64: 4 | U64: 4 | V64: 3 | W64: 3 | X64: 4 | Y64: 4 | Z64: 5 | AA64: 5 | AB64: 3 | AC64: 3 | AD64: 3 | AE64: 3 | AF64: 3 | AG64: 4 | AH64: 3 | AI64: 3 | AJ64: 2 | AK64: 2 | AL64: Training | AM64: limited skills in content creation
A65: 64 | B65: Treasurer | C65: 41-50 | D65: Female | E65: High School Grad | F65: 1-2 yrs | G65: Magsasakang Masisipag ng Mapanas (3M) Association | H65: 1-2 yrs | I65: 21-30 members | J65: 1-2 ha | K65: Fresh vegetables, Corn | L65: No | M65: Trader, Direct selling, Online | N65: 10,001 - 20,000 | O65: Yes | P65: Both Mobile & WiFi | Q65: No | S65: 5 | T65: 4 | U65: 4 | V65: 4 | W65: 4 | X65: 5 | Y65: 5 | Z65: 5 | AA65: 5 | AB65: 4 | AC65: 3 | AD65: 4 | AE65: 5 | AF65: 4 | AG65: 5 | AH65: 3 | AI65: 3 | AJ65: 2 | AK65: 3 | AL65: Training, tools | AM65: Lack of tools for product photography
... A79: 78 | B79: Member | C79: 41-50 | D79: Female | E79: High School Grad | F79: 1-2 yrs | G79: Manraya Fisherfolks and Farmers Association | H79: 1-2 yrs | I79: 21-30 members | J79: less than 1 ha | K79: Livestock | L79: No | M79: Direct selling | N79: Above 20,000 | O79: Yes | P79: Mobile data | Q79: No | S79: 4 | T79: 4 | U79: 4 | V79: 3 | W79: 3 | X79: 4 | Y79: 4 | Z79: 4 | AA79: 4 | AB79: 3 | AC79: 3 | AD79: 3 | AE79: 5 | AF79: 3 | AG79: 3 | AH79: 3 | AI79: 3 | AJ79: 3 | AK79: 3 | AL79: Training, internet connection, tools | AM79: limited skills, unstable internet connection
A80: 79 | B80: President | C80: 51 & above | D80: Male | E80: High School Graduate | F80: 3-5 yrs | G80: Bolusao Coconut Based Integrated FA | H80: 3-5 yrs | I80: 11-20 members | J80: 1-2 ha | K80: Poultry, Processed products | L80: Yes; Tablea, Chocolate, sandwich spread | M80: Trader, Direct selling, online | N80: Above 20,000 | O80: Yes | P80: Both Mobile & WiFi | Q80: Yes | R80: Posting products on social media | S80: 3 | T80: 3 | U80: 3 | V80: 3 | W80: 3 | X80: 3 | Y80: 4 | Z80: 4 | AA80: 4 | AB80: 3 | AC80: 3 | AD80: 3 | AE80: 5 | AF80: 3 | AG80: 3 | AH80: 3 | AI80: 4 | AJ80: 3 | AK80: 3 | AL80: Additional training, stable internet connection | AM80: lack of strategy
A81: 80 | B81: Member | C81: 41-50 | D81: Male | E81: College Graduate | F81: 3-5 yrs | G81: Bolusao Coconut Based Integrated FA | H81: 3-5 yrs | I81: 11-20 members | J81: 1-2 ha | K81: Poultry, Processed products | L81: Yes; Tablea, Chocolate, sandwich spread | M81: Trader, Direct selling, online | N81: Above 20,000 | O81: Yes | P81: Both Mobile & WiFi | Q81: Yes | R81: Posting products on social media | S81: 3 | T81: 3 | U81: 3 | V81: 3 | W81: 3 | X81: 4 | Y81: 4 | Z81: 4 | AA81: 4 | AB81: 3 | AC81: 3 | AD81: 3 | AE81: 4 | AF81: 4 | AG81: 4 | AH81: 2 | AI81: 4 | AJ81: 3 | AK81: 2 | AL81: Additional training, stable internet connection | AM81: lack of strategy
A82: 81 | B82: President | C82: 41-50 | D82: Female | E82: College Graduate | F82: 3-5 yrs | G82: San Isidro Women's Association | H82: 3-5 yrs | I82: 11-20 members | J82: 1-2 ha | K82: Fresh vegetables, Poultry, Processed products | L82: Yes; Cassava cake | M82: Trader, Direct selling, Institutional buyer, Online | N82: Above 20,000 | O82: Yes | P82: Both Mobile & WiFi | Q82: No | S82: 4 | T82: 3 | U82: 3 | V82: 3 | W82: 3 | X82: 4 | Y82: 4 | Z82: 4 | AA82: 3 | AB82: 3 | AC82: 4 | AD82: 3 | AE82: 5 | AF82: 5 | AG82: 5 | AH82: 3 | AI82: 4 | AJ82: 3 | AK82: 3 | AL82: Training, tools, stable internet connection | AM82: limited skills and usage of digital marketing
A83: 82 | B83: Secretary | C83: 41-50 | D83: Female | E83: High School Grad | F83: 3-5 yrs | G83: San Isidro Women's Association | H83: 3-5 yrs | I83: 11-20 members | J83: 1-2 ha | K83: Fresh vegetables, Poultry, Processed products | L83: Yes; Cassava cake | M83: Trader, Direct selling, Institutional buyer, Online | N83: Above 20,000 | O83: Yes | P83: Both Mobile & WiFi | Q83: No | S83: 4 | T83: 3 | U83: 4 | V83: 3 | W83: 3 | X83: 4 | Y83: 4 | Z83: 4 | AA83: 4 | AB83: 4 | AC83: 3 | AD83: 3 | AE83: 4 | AF83: 4 | AG83: 5 | AH83: 3 | AI83: 3 | AJ83: 3 | AK83: 3 | AL83: Training, tools, stable internet connection | AM83: limited skills, unstable internet connection
A84: 83 | B84: President | C84: 41-50 | D84: Female | E84: High School Level | F84: 1-2 yrs | G84: Sagkaray Farmers and Development Association | H84: 1-2 yrs | I84: 11-20 members | J84: 1-2 ha | K84: Fresh vegetables, processed products | L84: Yes; tablea | M84: Trader, Direct selling, Institutional buyer, Online | N84: 5,001 - 10,000 | O84: Yes | P84: Mobile data | Q84: No | S84: 3 | T84: 3 | U84: 3 | V84: 3 | W84: 3 | X84: 4 | Y84: 4 | Z84: 4 | AA84: 4 | AB84: 3 | AC84: 3 | AD84: 3 | AE84: 4 | AF84: 4 | AG84: 4 | AH84: 2 | AI84: 4 | AJ84: 3 | AK84: 2 | AL84: Training, tools, stable internet connection | AM84: limited skills, unstable internet connection
A85: 84 | B85: Treasurer | C85: 41-50 | D85: Female | E85: High School Level | F85: 1-2 yrs | G85: Sagkaray Farmers and Development Association | H85: 1-2 yrs | I85: 11-20 members | J85: 1-2 ha | K85: Fresh vegetables, processed products | L85: Yes; tablea | M85: Trader, Direct selling, Institutional buyer, Online | N85: 5,001 - 10,000 | O85: Yes | P85: Mobile data | Q85: No | S85: 5 | T85: 4 | U85: 5 | V85: 3 | W85: 3 | X85: 3 | Y85: 5 | Z85: 3 | AA85: 3 | AB85: 3 | AC85: 3 | AD85: 3 | AE85: 3 | AF85: 3 | AG85: 3 | AH85: 2 | AI85: 3 | AJ85: 2 | AK85: 2 | AL85: Training, tools/devices | AM85: limited skills
A86: 85 | B86: President | C86: 41-50 | D86: Male | E86: High School Grad | F86: 1-2 yrs | G86: Tanglad Farmers Association | H86: 1-2 yrs | I86: 11-20 members | J86: 1-2 ha | K86: Fresh vegetables, Poultry | L86: No | M86: Trader, Direct selling | N86: Above 20,000 | O86: Yes | P86: Mobile data | Q86: No | S86: 5 | T86: 5 | U86: 5 | V86: 4 | W86: 3 | X86: 4 | Y86: 4 | Z86: 4 | AA86: 4 | AB86: 4 | AC86: 3 | AD86: 3 | AE86: 4 | AF86: 3 | AG86: 4 | AH86: 3 | AI86: 2 | AJ86: 2 | AK86: 2 | AL86: Training, tools/devices | AM86: limited skills
A87: 86 | B87: Secretary | C87: 31-40 | D87: Female | E87: High School Grad | F87: 1-2 yrs | G87: Tanglad Farmers Association | H87: 1-2 yrs | I87: 11-20 members | J87: 1-2 ha | K87: Fresh vegetables, Poultry | L87: No | M87: Trader, Direct selling | N87: Above 20,000 | O87: Yes | P87: Mobile data | Q87: No | S87: 4 | T87: 4 | U87: 4 | V87: 3 | W87: 3 | X87: 4 | Y87: 4 | Z87: 4 | AA87: 4 | AB87: 3 | AC87: 3 | AD87: 3 | AE87: 5 | AF87: 3 | AG87: 3 | AH87: 3 | AI87: 3 | AJ87: 3 | AK87: 3 | AL87: tools/ device | AM87: limited tools/ gadgets
A88: 87 | B88: President | C88: 41-50 | D88: Male | E88: High School Level | F88: 1-2 yrs | G88: Buyayawon Farmers Association | H88: 1-2 yrs | I88: 11-20 members | J88: less than 1 ha | K88: Poultry | L88: No | M88: Direct selling, Instituional buyer, online | N88: Above 20,000 | O88: Yes | P88: Mobile data | Q88: No | S88: 3 | T88: 3 | U88: 3 | V88: 3 | W88: 3 | X88: 3 | Y88: 4 | Z88: 4 | AA88: 4 | AB88: 3 | AC88: 3 | AD88: 3 | AE88: 5 | AF88: 3 | AG88: 3 | AH88: 3 | AI88: 4 | AJ88: 3 | AK88: 3 | AL88: tools/ device | AM88: limited tools/ gadgets
A89: 88 | B89: Treasurer | C89: 41-50 | D89: Female | E89: High School Grad | F89: 1-2 yrs | G89: Buyayawon Farmers Association | H89: 1-2 yrs | I89: 11-20 members | J89: less than 1 ha | K89: Poultry | L89: No | M89: Direct selling, Instituional buyer, online | N89: Above 20,000 | O89: Yes | P89: Mobile data | Q89: No | S89: 4 | T89: 3 | U89: 3 | V89: 3 | W89: 3 | X89: 5 | Y89: 3 | Z89: 5 | AA89: 4 | AB89: 3 | AC89: 5 | AD89: 4 | AE89: 4 | AF89: 3 | AG89: 4 | AH89: 2 | AI89: 3 | AJ89: 2 | AK89: 2 | AL89: tools/ device | AM89: limited tools/ gadgets
A90: 89 | B90: President | C90: 51 & above | D90: Male | E90: High School Level | F90: 1-2 yrs | G90: Bangon-Alugan-Tanauan-Sta. Cruz Corn and Cassava FA | H90: 1-2 yrs | I90: 21-30 members | J90: less than 1 ha | K90: Poultry | L90: No | M90: Direct selling, Instituional buyer, online | N90: Above 20,000 | O90: Yes | P90: Mobile data | Q90: No | S90: 4 | T90: 3 | U90: 3 | V90: 4 | W90: 4 | X90: 4 | Y90: 4 | Z90: 4 | AA90: 3 | AB90: 3 | AC90: 5 | AD90: 3 | AE90: 3 | AF90: 3 | AG90: 3 | AH90: 1 | AI90: 2 | AJ90: 1 | AK90: 1 | AL90: Training, tools/devices | AM90: limited skills
A91: 90 | B91: Treasurer | C91: 41-50 | D91: Female | E91: High School Level | F91: 1-2 yrs | G91: Bangon-Alugan-Tanauan-Sta. Cruz Corn and Cassava FA | H91: 1-2 yrs | I91: 21-30 members | J91: less than 1 ha | K91: Poultry | L91: No | M91: Direct selling, Instituional buyer, online | N91: Above 20,000 | O91: Yes | P91: Mobile data | Q91: No | S91: 5 | T91: 4 | U91: 4 | V91: 3 | W91: 3 | X91: 4 | Y91: 4 | Z91: 3 | AA91: 4 | AB91: 4 | AC91: 3 | AD91: 3 | AE91: 3 | AF91: 3 | AG91: 3 | AH91: 2 | AI91: 4 | AJ91: 2 | AK91: 2 | AL91: Training, tools/devices | AM91: limited skills
A92: 91 | B92: President | C92: 41-50 | D92: Female | E92: Elementary Level | F92: 3-5 yrs | G92: Mabuhay Farmers Peace Builders and Development Association | H92: 3-5 yrs | I92: 21-30 members | J92: less than 1 ha | K92: Poultry | L92: No | M92: Trader, Direct selling | N92: Above 20,000 | O92: Yes | P92: WiFi | Q92: No | S92: 5 | T92: 4 | U92: 4 | V92: 3 | W92: 3 | X92: 4 | Y92: 5 | Z92: 5 | AA92: 4 | AB92: 5 | AC92: 5 | AD92: 5 | AE92: 4 | AF92: 3 | AG92: 4 | AH92: 2 | AI92: 3 | AJ92: 2 | AK92: 2 | AL92: Tools, stable internet connection | AM92: limited digital skills
A93: 92 | B93: Business Manager | C93: 41-50 | D93: Male | E93: High School Level | F93: 3-5 yrs | G93: Mabuhay Farmers Peace Builders and Development Association | H93: 3-5 yrs | I93: 21-30 members | J93: less than 1 ha | K93: Poultry | L93: No | M93: Trader, Direct selling | N93: Above 20,000 | O93: Yes | P93: WiFi | Q93: No | S93: 5 | T93: 4 | U93: 4 | V93: 4 | W93: 3 | X93: 4 | Y93: 5 | Z93: 5 | AA93: 5 | AB93: 5 | AC93: 5 | AD93: 5 | AE93: 3 | AF93: 4 | AG93: 4 | AH93: 1 | AI93: 2 | AJ93: 2 | AK93: 1 | AL93: Tools, stable internet connection | AM93: limited digital skills
... A95: 94 | B95: Treasurer | C95: 31-40 | D95: Female | E95: High School Level | F95: 3-5 yrs | G95: Kapit Bisig Tungo sa Pag-unlad ng Mamamayan Farmers and Fisherfolks Association | H95: 3-5 yrs | I95: 21-30 members | J95: 1-2 ha | K95: Fresh vegetables, Poultry | L95: No | M95: Public market, Direct selling, Online | N95: Above 20,000 | O95: Yes | P95: Mobile data | Q95: No | S95: 4 | T95: 3 | U95: 3 | V95: 3 | W95: 3 | X95: 3 | Y95: 5 | Z95: 4 | AA95: 3 | AB95: 4 | AC95: 4 | AD95: 4 | AE95: 4 | AF95: 4 | AG95: 4 | AH95: 3 | AI95: 3 | AJ95: 2 | AK95: 3 | AL95: Training, tools/devices | AM95: limited skills
A96: 95 | B96: President | C96: 18-30 | D96: Male | E96: College Grad | F96: 3-5 yrs | G96: Casapa Livestock Raisers Association (CLiRA) | H96: 3-5 yrs | I96: 21-30 members | J96: less than 1 ha | K96: Poultry | L96: No | M96: Trader, Direct selling, Online | N96: Above 20,000 | O96: Yes | P96: Mobile data | Q96: Yes | R96: Posting products on social media | S96: 3 | T96: 3 | U96: 3 | V96: 2 | W96: 2 | X96: 3 | Y96: 2 | Z96: 2 | AA96: 3 | AB96: 2 | AC96: 2 | AD96: 2 | AE96: 1 | AF96: 2 | AG96: 2 | AH96: 4 | AI96: 4 | AJ96: 4 | AK96: 4 | AL96: proper tools/ equipment to improve content creation | AM96: Limited tools /resources
A97: 96 | B97: Member | C97: 18-30 | D97: Male | E97: College Grad | F97: 3-5 yrs | G97: Casapa Livestock Raisers Association (CLiRA) | H97: 3-5 yrs | I97: 21-30 members | J97: less than 1 ha | K97: Poultry | L97: No | M97: Trader, Direct selling, Online | N97: Above 20,000 | O97: Yes | P97: WiFi | Q97: Yes | R97: Posting products on social media | S97: 4 | T97: 3 | U97: 3 | V97: 3 | W97: 2 | X97: 3 | Y97: 2 | Z97: 2 | AA97: 3 | AB97: 2 | AC97: 2 | AD97: 2 | AE97: 2 | AF97: 2 | AG97: 2 | AH97: 4 | AI97: 4 | AJ97: 4 | AK97: 4 | AL97: Additonal training, stable internet connection, tools/ equipment | AM97: limited content creation skills, unstable internet connection
A98: 97 | B98: President | C98: 41-50 | D98: Female | E98: High School Level | F98: 1-2 yrs | G98: Kauswagan Crop Farmers Association | H98: 1-2 yrs | I98: 11-20 members | J98: 1-2 ha | K98: Fresh vegetables | L98: No | M98: Trader, Direct selling | N98: Below 5,000 | O98: Yes | P98: Mobile data | Q98: No | S98: 4 | T98: 3 | U98: 3 | V98: 3 | W98: 3 | X98: 5 | Y98: 3 | Z98: 5 | AA98: 4 | AB98: 3 | AC98: 5 | AD98: 4 | AE98: 4 | AF98: 3 | AG98: 4 | AH98: 2 | AI98: 3 | AJ98: 2 | AK98: 2 | AL98: stable internet connection, tools | AM98: limited skills/ experience
A99: 98 | B99: Member | C99: 31-40 | D99: Female | E99: High School Level | F99: 1-2 yrs | G99: Kauswagan Crop Farmers Association | H99: 1-2 yrs | I99: 11-20 members | J99: 1-2 ha | K99: Fresh vegetables | L99: No | M99: Trader, Direct selling | N99: Below 5,000 | O99: Yes | P99: Mobile data | Q99: No | S99: 4 | T99: 3 | U99: 3 | V99: 4 | W99: 4 | X99: 4 | Y99: 4 | Z99: 4 | AA99: 3 | AB99: 3 | AC99: 5 | AD99: 3 | AE99: 3 | AF99: 3 | AG99: 3 | AH99: 1 | AI99: 2 | AJ99: 1 | AK99: 1 | AL99: stable internet connection, tools | AM99: limited skills/ experience
A100: 99 | B100: President | C100: 51 & above | D100: Male | E100: Elementray Graduate | F100: 1-2 yrs | G100: Calanyugan Farmers Association | H100: 1-2 yrs | I100: 11-20 members | J100: 1-2 ha | K100: Fresh vegetables, Poultry | L100: No | M100: Trader, Direct selling | N100: Above 20,000 | O100: Yes | P100: WiFi | Q100: No | S100: 5 | T100: 4 | U100: 4 | V100: 3 | W100: 3 | X100: 4 | Y100: 4 | Z100: 3 | AA100: 4 | AB100: 4 | AC100: 3 | AD100: 3 | AE100: 3 | AF100: 3 | AG100: 3 | AH100: 2 | AI100: 4 | AJ100: 2 | AK100: 2 | AL100: training | AM100: transportation for product delivery
A101: 100 | B101: Secretary | C101: 41-50 | D101: Female | E101: High School Graduate | F101: 1-2 yrs | G101: Calanyugan Farmers Association | H101: 1-2 yrs | I101: 11-20 members | J101: 1-2 ha | K101: Fresh vegetables, Poultry | L101: No | M101: Trader, Direct selling | N101: Above 20,000 | O101: Yes | P101: Mobile data | Q101: No | S101: 3 | T101: 3 | U101: 3 | V101: 3 | W101: 3 | X101: 4 | Y101: 4 | Z101: 4 | AA101: 4 | AB101: 3 | AC101: 3 | AD101: 3 | AE101: 4 | AF101: 4 | AG101: 4 | AH101: 2 | AI101: 4 | AJ101: 3 | AK101: 2 | AL101: training | AM101: transportation for product delivery
A102: 101 | B102: Secretary | C102: 41-50 | D102: Female | E102: High School Graduate | F102: 1-2 yrs | G102: Brgy. Lunang II Farmers and Fisherfolks Association | H102: 1-2 yrs | I102: 21-30 members | J102: less than 1 ha | K102: Fresh vegetables, Poultry | L102: No | M102: Trader, Direct selling, Online | N102: Above 20,000 | O102: Yes | P102: Both Mobile & WiFi | Q102: No | S102: 5 | T102: 5 | U102: 5 | V102: 4 | W102: 3 | X102: 4 | Y102: 4 | Z102: 4 | AA102: 4 | AB102: 4 | AC102: 3 | AD102: 3 | AE102: 4 | AF102: 3 | AG102: 4 | AH102: 3 | AI102: 2 | AJ102: 2 | AK102: 2 | AL102: training, stable internet connection | AM102: lack of strategy
A103: 102 | B103: Treasurer | C103: 41-50 | D103: Female | E103: High School Graduate | F103: 1-2 yrs | G103: Brgy. Lunang II Farmers and Fisherfolks Association | H103: 1-2 yrs | I103: 21-30 members | J103: less than 1 ha | K103: Fresh vegetables, Poultry | L103: No | M103: Trader, Direct selling, Online | N103: Above 20,000 | O103: Yes | P103: Both Mobile & WiFi | Q103: No | S103: 4 | T103: 4 | U103: 4 | V103: 3 | W103: 3 | X103: 4 | Y103: 4 | Z103: 4 | AA103: 4 | AB103: 3 | AC103: 3 | AD103: 3 | AE103: 5 | AF103: 3 | AG103: 3 | AH103: 3 | AI103: 3 | AJ103: 3 | AK103: 3 | AL103: training, stable internet connection | AM103: lack of strategy
A104: 103 | B104: President | C104: 51 & above | D104: Male | E104: High School Graduate | F104: 3-5 yrs | G104: Barangay Pinalangga Fishermens and Farmers Association | H104: 3-5 yrs | I104: 21-30 members | J104: less than 1 ha | K104: Livestock; Processed products | L104: Yes; tocino | M104: Trader, Direct selling, Online | N104: Above 20,000 | O104: Yes | P104: Both Mobile & WiFi | Q104: No | S104: 3 | T104: 3 | U104: 3 | V104: 3 | W104: 3 | X104: 3 | Y104: 4 | Z104: 4 | AA104: 4 | AB104: 3 | AC104: 3 | AD104: 3 | AE104: 5 | AF104: 3 | AG104: 3 | AH104: 3 | AI104: 4 | AJ104: 3 | AK104: 3 | AL104: training | AM104: transportation for product delivery
A105: 104 | B105: Secretary | C105: 41-50 | D105: Female | E105: High School | F105: 3-5 yrs | G105: Barangay Pinalangga Fishermens and Farmers Association | H105: 3-5 yrs | I105: 21-30 members | J105: less than 1 ha | K105: Livestock; Processed products | L105: Yes; tocino | M105: Trader, Direct selling, Online | N105: Above 20,000 | O105: Yes | P105: Both Mobile & WiFi | Q105: No | S105: 4 | T105: 3 | U105: 3 | V105: 3 | W105: 3 | X105: 5 | Y105: 3 | Z105: 5 | AA105: 4 | AB105: 3 | AC105: 5 | AD105: 4 | AE105: 4 | AF105: 3 | AG105: 4 | AH105: 2 | AI105: 3 | AJ105: 2 | AK105: 2 | AL105: training | AM105: transportation for product delivery
A106: 105 | B106: President | C106: 31-40 | D106: Female | E106: College Graduate | F106: 1-2 yrs | G106: Balocawe Hog Raisers Association | H106: 1-2 yrs | I106: 11-20 members | J106: less than 1 ha | K106: Livestock | L106: No | M106: Trader, Direct selling | N106: Above 20,000 | O106: Yes | P106: Both Mobile & WiFi | Q106: No | S106: 4 | T106: 3 | U106: 3 | V106: 4 | W106: 4 | X106: 4 | Y106: 4 | Z106: 4 | AA106: 3 | AB106: 3 | AC106: 5 | AD106: 3 | AE106: 3 | AF106: 3 | AG106: 3 | AH106: 1 | AI106: 2 | AJ106: 1 | AK106: 1 | AL106: stable internet connection, tools | AM106: limited skills/ experience
A107: 106 | B107: Secretary | C107: 31-40 | D107: Female | E107: High School Graduate | F107: 1-2 yrs | G107: Balocawe Hog Raisers Association | H107: 1-2 yrs | I107: 11-20 members | J107: less than 1 ha | K107: Livestock | L107: No | M107: Trader, Direct selling | N107: Above 20,000 | O107: Yes | P107: Both Mobile & WiFi | Q107: No | S107: 5 | T107: 4 | U107: 4 | V107: 3 | W107: 3 | X107: 4 | Y107: 4 | Z107: 3 | AA107: 4 | AB107: 4 | AC107: 3 | AD107: 3 | AE107: 3 | AF107: 3 | AG107: 3 | AH107: 2 | AI107: 4 | AJ107: 2 | AK107: 2 | AL107: stable internet connection, tools | AM107: limited skills/ experience
A108: 107 | B108: President | C108: 31-40 | D108: Male | E108: College Graduate | F108: 1-2 yrs | G108: Balogo Integrated Farmers Association | H108: 1-2 yrs | I108: 11-20 members | J108: less than 1 ha | K108: Poultry | L108: No | M108: Direct selling, Trader, Online | N108: Above 20,000 | O108: Yes | P108: WiFi | Q108: No | S108: 4 | T108: 3 | U108: 4 | V108: 3 | W108: 3 | X108: 3 | Y108: 4 | Z108: 4 | AA108: 4 | AB108: 3 | AC108: 4 | AD108: 3 | AE108: 4 | AF108: 4 | AG108: 4 | AH108: 3 | AI108: 2 | AJ108: 2 | AK108: 2 | AL108: stable internet connection, tools | AM108: not consistently using digital marketing
A109: 108 | B109: Treasurer | C109: 31-40 | D109: Female | E109: High School Grad | F109: 1-2 yrs | G109: Balogo Integrated Farmers Association | H109: 1-2 yrs | I109: 11-20 members | J109: less than 1 ha | K109: Poultry | L109: No | M109: Direct selling, Trader, Online | N109: Above 20,000 | O109: Yes | P109: WiFi | Q109: No | S109: 4 | T109: 4 | U109: 4 | V109: 4 | W109: 4 | X109: 4 | Y109: 4 | Z109: 4 | AA109: 4 | AB109: 3 | AC109: 4 | AD109: 4 | AE109: 4 | AF109: 4 | AG109: 4 | AH109: 3 | AI109: 3 | AJ109: 2 | AK109: 2 | AL109: stable internet connection, tools | AM109: limited skills/ experience

Sheet lkrt-data
A1: statement | B1: items | C1: factor
A2: Unreliable internet connectivity limits our enterprise’s ability to conduct digital marketing activities. | B2: TB1 | C2: Technological barriers
A3: Unreliable internet connectivity limits our enterprise’s ability to conduct digital marketing activities. | B3: TB2 | C3: Technological barriers
A4: The available internet and digital facilities are insufficient to support our enterprise’s digital marketing activities. | B4: TB3 | C4: Technological barriers
A5: Digital marketing tools are difficult for our enterprise to understand. | B5: TB4 | C5: Technological barriers
A6: Digital marketing platforms are complicated for our enterprise to use. | B6: TB5 | C6: Technological barriers
A7: Managing multiple digital marketing platforms is complicated for our enterprise. | B7: TB6 | C7: Technological barriers
A8: Members of our enterprise lack the digital skills needed to carry out digital marketing activities. | B8: OB7 | C8: Organizational barriers
A9: Few members of our enterprise are capable of managing digital marketing tools effectively. | B9: OB8 | C9: Organizational barriers
A10: Our enterprise has limited knowledge in creating and managing online marketing content. | B10: OB9 | C10: Organizational barriers
A11: The leaders of our enterprise do not strongly encourage the use of digital marketing. | B11: OB10 | C11: Organizational barriers
A12: Our enterprise leaders provide limited guidance for implementing digital marketing activities. | B12: OB11 | C12: Organizational barriers
... A20: Our enterprise interacts with customers online by responding to comments, messages, or feedback on digital platforms. | B20: DMA19 | C20: Digital marketing adoption

Sheet Raw Data
A1: Respondent No. | B1: Role | C1: Age_Range | D1: Sex | E1: Education | F1: Years_Managing | G1: Organization_Name | H1: Years_Established | I1: Membership _Size | J1: Farm_Size | K1: Commodity | L1: Value_Adding/ Processed_ Products_Specify | M1: Market | N1: Income_Level | O1: Has_Device | P1: Internet_ Type | Q1: Attended_Training | R1: Training_Details | S1: TB1 | T1: TB2 | U1: TB3 | V1: TB4 | W1: TB5 | X1: TB6 | Y1: OB7 | Z1: OB8 | AA1: OB9 | AB1: OB10 | AC1: OB11 | AD1: OB12 | AE1: EB13 | AF1: EB14 | AG1: EB15 | AH1: DMA16 | AI1: DMA17 | AJ1: DMA18 | AK1: DMA19 | AL1: Support_ Suggestions | AM1: Challenges
A2: 1 | B2: President | C2: 51 & above | D2: Male | E2: High School Grad | F2: 1-2 yrs | G2: Sampao Small Water Irrigation System Association, Inc. | H2: 1-2 yrs | I2: 11-20 members | J2: 1-2 ha | K2: Fresh Vegetables, Corn | L2: No | M2: Public market, Direct selling, Trader, Online | N2: Above 20,000 | O2: Yes | P2: WiFi | Q2: No | S2: 4 | T2: 5 | U2: 4 | V2: 4 | W2: 4 | X2: 4 | Y2: 5 | Z2: 5 | AA2: 5 | AB2: 3 | AC2: 3 | AD2: 3 | AE2: 4 | AF2: 3 | AG2: 4 | AH2: 3 | AI2: 3 | AJ2: 2 | AK2: 3 | AL2: Training, stable internet connection, tools | AM2: Unstable internet connection, limited manpower for digital marketing
A3: =A2+1 -> 2 | B3: Treasurer | C3: 41-50 | D3: Female | E3: High School Grad | F3: 1-2 yrs | G3: Sampao Small Water Irrigation System Association, Inc. | H3: 1-2 yrs | I3: 11-20 members | J3: 1-2 ha | K3: Fresh Vegetables, Corn | L3: No | M3: Public market, Direct selling, Trader, Online | N3: Above 20,000 | O3: Yes | P3: WiFi | Q3: No | S3: 5 | T3: 5 | U3: 4 | V3: 4 | W3: 4 | X3: 4 | Y3: 4 | Z3: 4 | AA3: 4 | AB3: 3 | AC3: 4 | AD3: 4 | AE3: 4 | AF3: 3 | AG3: 3 | AH3: 2 | AI3: 3 | AJ3: 2 | AK3: 2 | AL3: Training, stable internet connection, tools | AM3: limited digital skills, Unstable internet connection
A4: =A3+1 -> 3 | B4: Secretary | C4: 41-50 | D4: Female | E4: High School Level | F4: 1-2 yrs | G4: Pinangomhan Farmers Association | H4: 1-2 yrs | I4: 21-30 members | J4: 1-2 ha | K4: Fresh vegetables, Poultry | L4: No | M4: Public market, Direct selling, Trader, Online | N4: Above 20,000 | O4: Yes | P4: WiFi | Q4: No | S4: 5 | T4: 4 | U4: 5 | V4: 3 | W4: 3 | X4: 5 | Y4: 4 | Z4: 5 | AA4: 4 | AB4: 3 | AC4: 3 | AD4: 3 | AE4: 4 | AF4: 4 | AG4: 4 | AH4: 3 | AI4: 3 | AJ4: 2 | AK4: 3 | AL4: Training, reliable tools/ devices | AM4: limited skills, unstable internet connection
A5: =A4+1 -> 4 | B5: President | C5: 51 & above | D5: Female | E5: High School Grad | F5: 1-2 yrs | G5: Pinangomhan Farmers Association | H5: 1-2 yrs | I5: 21-30 members | J5: 1-2 ha | K5: Fresh vegetables, Poultry | L5: No | M5: Public market, Direct selling, Trader, Online | N5: Above 20,000 | O5: Yes | P5: WiFi | Q5: No | S5: 5 | T5: 5 | U5: 5 | V5: 4 | W5: 3 | X5: 4 | Y5: 4 | Z5: 4 | AA5: 4 | AB5: 4 | AC5: 3 | AD5: 3 | AE5: 4 | AF5: 3 | AG5: 4 | AH5: 3 | AI5: 2 | AJ5: 2 | AK5: 2 | AL5: Training | AM5: unstable internet connection
A6: =A5+1 -> 5 | B6: BOD | C6: 41-50 | D6: Male | E6: High School Grad | F6: 3-5 yrs | G6: Culaba Integrated Hilltop Farm | H6: 1-2 yrs | I6: 21-30 members | J6: less than 1 ha | K6: Fresh vegetables | L6: No | M6: Direct selling, Online | N6: less than 5,000 | O6: Yes | P6: Both Mobile & WiFi | Q6: No | S6: 4 | T6: 4 | U6: 4 | V6: 3 | W6: 3 | X6: 4 | Y6: 4 | Z6: 4 | AA6: 4 | AB6: 3 | AC6: 3 | AD6: 3 | AE6: 5 | AF6: 3 | AG6: 3 | AH6: 3 | AI6: 3 | AJ6: 3 | AK6: 3 | AL6: Training and more stable internet connection | AM6: unstable internet connection
A7: =A6+1 -> 6 | B7: Secretary | C7: 31-40 | D7: Female | E7: High School Grad | F7: 3-5 yrs | G7: Culaba Integrated Hilltop Farm | H7: 1-2 yrs | I7: 21-30 members | J7: less than 1 ha | K7: Fresh vegetables | L7: No | M7: Direct selling, Online | N7: less than 5,000 | O7: Yes | P7: Both Mobile & WiFi | Q7: No | S7: 3 | T7: 3 | U7: 3 | V7: 3 | W7: 3 | X7: 3 | Y7: 4 | Z7: 4 | AA7: 4 | AB7: 3 | AC7: 3 | AD7: 3 | AE7: 5 | AF7: 3 | AG7: 3 | AH7: 3 | AI7: 4 | AJ7: 3 | AK7: 3 | AL7: Training and more stable internet connection | AM7: unstable internet connection
A8: =A7+1 -> 7 | B8: President | C8: 51 & above | D8: Female | E8: High School Grad | F8: 3-5 yrs | G8: Cabucgayan Farmers Association (CAFA) | H8: 3-5 yrs | I8: 21-30 members | J8: 1-2 ha | K8: Fresh Vegetables, Corn | L8: No | M8: Public market, Direct selling, Trader | N8: 10,001 - 20,000 | O8: Yes | P8: None | Q8: No | S8: 5 | T8: 4 | U8: 5 | V8: 3 | W8: 4 | X8: 5 | Y8: 5 | Z8: 5 | AA8: 5 | AB8: 4 | AC8: 4 | AD8: 4 | AE8: 4 | AF8: 4 | AG8: 4 | AH8: 1 | AI8: 2 | AJ8: 1 | AK8: 1 | AL8: Training, Internet Access | AM8: No internet access, and experience in Digital marketing
A9: =A8+1 -> 8 | B9: Treasurer | C9: 41-50 | D9: Female | E9: High School Grad | F9: 3-5 yrs | G9: Cabucgayan Farmers Association (CAFA) | H9: 3-5 yrs | I9: 21-30 members | J9: 1-2 ha | K9: Fresh Vegetables, Corn | L9: No | M9: Public market, Direct selling, Trader | N9: 10,001 - 20,001 | O9: Yes | P9: None | Q9: No | S9: 5 | T9: 5 | U9: 5 | V9: 4 | W9: 5 | X9: 5 | Y9: 5 | Z9: 5 | AA9: 5 | AB9: 4 | AC9: 3 | AD9: 4 | AE9: 4 | AF9: 4 | AG9: 4 | AH9: 1 | AI9: 2 | AJ9: 2 | AK9: 1 | AL9: Training, Internet Access | AM9: No internet access, and experience in Digital marketing
A10: =A9+1 -> 9 | B10: President | C10: 51 & above | D10: Male | E10: College Graduate | F10: 1-2 yrs | G10: Samahan ng mga Manggagawa Para sa Agrikulturang Pangkabuhayan (SMAP) | H10: 1-2 yrs | I10: 11-20 members | J10: 1-2 ha | K10: Fresh Vegetables, Corn | L10: No | M10: Public market, Direct selling, Trader | N10: 5,001 - 10,000 | O10: Yes | P10: WiFi | Q10: No | S10: 5 | T10: 4 | U10: 4 | V10: 4 | W10: 4 | X10: 4 | Y10: 4 | Z10: 4 | AA10: 4 | AB10: 3 | AC10: 4 | AD10: 4 | AE10: 4 | AF10: 3 | AG10: 4 | AH10: 2 | AI10: 2 | AJ10: 2 | AK10: 2 | AL10: Training, internet connection, tools | AM10: limited skills, unstable internet connection
A11: =A10+1 -> 10 | B11: Secretary | C11: 31-40 | D11: Female | E11: College Level | F11: 1-2 yrs | G11: Samahan ng mga Manggagawa Para sa Agrikulturang Pangkabuhayan (SMAP) | H11: 1-2 yrs | I11: 11-20 members | J11: 1-2 ha | K11: Fresh Vegetables, Corn | L11: No | M11: Public market, Direct selling, Trader | N11: 5,001 - 10,001 | O11: Yes | P11: Mobile data | Q11: No | S11: 4 | T11: 4 | U11: 4 | V11: 4 | W11: 4 | X11: 4 | Y11: 5 | Z11: 5 | AA11: 5 | AB11: 4 | AC11: 3 | AD11: 3 | AE11: 3 | AF11: 3 | AG11: 3 | AH11: 1 | AI11: 2 | AJ11: 1 | AK11: 1 | AL11: Training, internet connection, tools | AM11: limited skills, unstable internet connection
A12: =A11+1 -> 11 | B12: President | C12: 51 & above | D12: Male | E12: High School Grad | F12: 1-2 yrs | G12: Tucdao-Anas Farmers’ Irrigator’s Association, Inc. | H12: 1-2 yrs | I12: 11-20 members | J12: 1-2 ha | K12: Fresh Vegetables, Corn | L12: No | M12: Public market, Direct selling, Trader | N12: Below 5,000 | O12: Yes | P12: WiFi | Q12: No | S12: 5 | T12: 4 | U12: 4 | V12: 3 | W12: 4 | X12: 4 | Y12: 3 | Z12: 4 | AA12: 4 | AB12: 4 | AC12: 3 | AD12: 3 | AE12: 4 | AF12: 4 | AG12: 4 | AH12: 2 | AI12: 3 | AJ12: 2 | AK12: 2 | AL12: Training, internet connection, tools | AM12: limited skills, unstable internet connection
A13: =A12+1 -> 12 | B13: Treasurer | C13: 41-50 | D13: Female | E13: High School Grad | F13: 1-2 yrs | G13: Tucdao-Anas Farmers’ Irrigator’s Association, Inc. | H13: 1-2 yrs | I13: 11-20 members | J13: 1-2 ha | K13: Fresh Vegetables, Corn | L13: No | M13: Public market, Direct selling, Trader | N13: Below 5,000 | O13: Yes | P13: WiFi | Q13: No | S13: 5 | T13: 5 | U13: 5 | V13: 4 | W13: 4 | X13: 4 | Y13: 4 | Z13: 5 | AA13: 5 | AB13: 4 | AC13: 3 | AD13: 3 | AE13: 3 | AF13: 3 | AG13: 3 | AH13: 2 | AI13: 3 | AJ13: 2 | AK13: 2 | AL13: Training, internet connection, tools | AM13: limited skills, unstable internet connection
A14: =A13+1 -> 13 | B14: President | C14: 41-50 | D14: Female | E14: High School Grad | F14: 1-2 yrs | G14: Maripipi Farmers and Fisherfolks Association | H14: 1-2 yrs | I14: 21-30 members | J14: 1-2 ha | K14: Fresh Vegetables, Corn | L14: No | M14: Public market, Direct selling, Trader | N14: 10,001 - 20,000 | O14: Yes | P14: Both Mobile & WiFi | Q14: No | S14: 4 | T14: 4 | U14: 4 | V14: 3 | W14: 4 | X14: 4 | Y14: 4 | Z14: 5 | AA14: 4 | AB14: 3 | AC14: 3 | AD14: 3 | AE14: 4 | AF14: 3 | AG14: 4 | AH14: 3 | AI14: 3 | AJ14: 3 | AK14: 3 | AL14: Training, stable internet connection | AM14: few members engage digital marketing, limited skills
... A23: =A22+1 -> 22 | B23: Secretary | C23: 41-50 | D23: Female | E23: College Grad | F23: 3-5 yrs | G23: Barangay Aringit Farmers Association | H23: 3-5 yrs | I23: 21-30 members | J23: 1-2 ha | K23: Fresh vegetables, Fruits, Poultry | L23: No | M23: Public market, Kadiwa ng Pangulo, Trader, Institutional buyer, Online | N23: 10,001 - 20,000 | O23: Yes | P23: Mobile data | Q23: No | S23: 5 | T23: 5 | U23: 3 | V23: 4 | W23: 4 | X23: 5 | Y23: 5 | Z23: 5 | AA23: 5 | AB23: 3 | AC23: 3 | AD23: 4 | AE23: 5 | AF23: 4 | AG23: 4 | AH23: 3 | AI23: 4 | AJ23: 3 | AK23: 3 | AL23: Training, Tools/ infrastructure, stable internet connection | AM23: limited skills & digital tools, unstable internet connection
A24: =A23+1 -> 23 | B24: President | C24: 31-40 | D24: Male | E24: College Level | F24: 1-2 yrs | G24: Julitanhon Integrated Farmers Association | H24: 1-2 yrs | I24: 11-20 members | J24: less than 1 ha | K24: Fresh vegetables, Poultry | L24: No | M24: Public market, Direct selling, Institutional buyer, Online | N24: Above 20,000 | O24: Yes | P24: Mobile data | Q24: Yes | R24: Posting products on social media | S24: 3 | T24: 4 | U24: 3 | V24: 3 | W24: 4 | X24: 5 | Y24: 4 | Z24: 5 | AA24: 5 | AB24: 3 | AC24: 4 | AD24: 4 | AE24: 4 | AF24: 4 | AG24: 4 | AH24: 3 | AI24: 3 | AJ24: 3 | AK24: 2 | AL24: tools/ infrastructure, additional training | AM24: few buyers online
A25: =A24+1 -> 24 | B25: Treasurer | C25: 31-40 | D25: Male | E25: Elementary Graduate | F25: 1-2 yrs | G25: Julitanhon Integrated Farmers Association | H25: 1-2 yrs | I25: 11-20 members | J25: less than 1 ha | K25: Fresh vegetables, Poultry | L25: No | M25: Public market, Direct selling, Trader, Online | N25: Above 20,000 | O25: Yes | P25: Mobile data | Q25: Yes | R25: Posting products on social media | S25: 3 | T25: 4 | U25: 4 | V25: 3 | W25: 3 | X25: 4 | Y25: 4 | Z25: 4 | AA25: 3 | AB25: 4 | AC25: 4 | AD25: 4 | AE25: 4 | AF25: 4 | AG25: 4 | AH25: 3 | AI25: 2 | AJ25: 3 | AK25: 2 | AL25: tools/ infrastructure, additional training | AM25: few buyers online
A26: =A25+1 -> 25 | B26: Secretary | C26: 51 & above | D26: Female | E26: High School Level | F26: 3-5 yrs | G26: Pagburublig han Parag-uma Association | H26: 3-5 yrs | I26: more than 30 | J26: 1-2 ha | K26: Fresh vegetables, Poultry, Processed products | L26: Yes; Banana chips, Virgin coconut oil | M26: Public market, Trader,Direct selling, Online | N26: Above 20,000 | O26: Yes | P26: Both Mobile & WiFi | Q26: Yes | R26: Posting products on social media | S26: 4 | T26: 3 | U26: 3 | V26: 3 | W26: 3 | X26: 4 | Y26: 3 | Z26: 4 | AA26: 5 | AB26: 3 | AC26: 4 | AD26: 4 | AE26: 3 | AF26: 4 | AG26: 3 | AH26: 3 | AI26: 4 | AJ26: 3 | AK26: 3 | AL26: Training, Tools/ infrastructure, stable internet connection | AM26: Higher fuel prices impact deliveries for online buyers
A27: =A26+1 -> 26 | B27: BOD | C27: 51 & above | D27: Female | E27: College Level | F27: 3-5 yrs | G27: Pagburublig han Parag-uma Association | H27: 3-5 yrs | I27: more than 30 | J27: 1-2 ha | K27: Fresh vegetables, Poultry, Processed products | L27: Yes; Banana chips, Virgin coconut oil | M27: Public market, Trader,Direct selling, Online | N27: Above 20,000 | O27: Yes | P27: Both Mobile & WiFi | Q27: Yes | R27: Posting products on social media | S27: 4 | T27: 3 | U27: 4 | V27: 3 | W27: 4 | X27: 4 | Y27: 3 | Z27: 4 | AA27: 3 | AB27: 3 | AC27: 4 | AD27: 4 | AE27: 3 | AF27: 4 | AG27: 4 | AH27: 3 | AI27: 3 | AJ27: 3 | AK27: 3 | AL27: Training, Tools/ infrastructure, stable internet connection | AM27: Higher fuel prices impact deliveries for online buyers
A28: =A27+1 -> 27 | B28: Secretary | C28: 31-40 | D28: Female | E28: College Grad | F28: 3-5 yrs | G28: Guingauan Small Farmers Association | H28: 3-5 yrs | I28: 11-20 members | J28: less than 1 ha | K28: Fresh vegetables | L28: No | M28: Trader, Direct selling | N28: Below 5,000 | O28: Yes | P28: Both Mobile & WiFi | Q28: No | S28: 4 | T28: 3 | U28: 4 | V28: 3 | W28: 4 | X28: 4 | Y28: 4 | Z28: 4 | AA28: 4 | AB28: 3 | AC28: 4 | AD28: 4 | AE28: 5 | AF28: 4 | AG28: 4 | AH28: 2 | AI28: 3 | AJ28: 3 | AK28: 2 | AL28: Training, Stable internet connection | AM28: Poor photo and writing skills for online marketing.
A29: =A28+1 -> 28 | B29: Member | C29: 41-50 | D29: Female | E29: High School Level | F29: 1-2 yrs | G29: Guingauan Small Farmers Association | H29: 3-5 y | I29: 11-20 members | J29: less than 1 ha | K29: Fresh vegetables | L29: No | M29: Trader, Direct selling | N29: Below 5,000 | O29: Yes | P29: Mobile data | Q29: No | S29: 5 | T29: 4 | U29: 4 | V29: 3 | W29: 3 | X29: 4 | Y29: 5 | Z29: 5 | AA29: 5 | AB29: 4 | AC29: 5 | AD29: 4 | AE29: 3 | AF29: 4 | AG29: 3 | AH29: 1 | AI29: 2 | AJ29: 1 | AK29: 1 | AL29: Training, Stable internet connection | AM29: Limited skills
A30: =A29+1 -> 29 | B30: President | C30: 51 & above | D30: Male | E30: Elementary Level | F30: 1-2 yrs | G30: Assuncion Del Senior Integrated Farmers Association | H30: 1-2 yrs | I30: 11-20 members | J30: less than 1 ha | K30: Fresh vegetables | L30: No | M30: Direct selling, Trader | N30: Below 5,000 | O30: Yes | P30: Mobile data | Q30: No | S30: 5 | T30: 5 | U30: 5 | V30: 5 | W30: 5 | X30: 5 | Y30: 5 | Z30: 5 | AA30: 5 | AB30: 3 | AC30: 5 | AD30: 4 | AE30: 4 | AF30: 4 | AG30: 4 | AH30: 1 | AI30: 2 | AJ30: 2 | AK30: 1 | AL30: Tools, internet access, Training | AM30: Lack of tools/devices, and skills
A31: =A30+1 -> 30 | B31: Treasurer | C31: 51 & above | D31: Female | E31: Elementary Graduate | F31: 1-2 yrs | G31: Assuncion Del Senior Integrated Farmers Association | H31: 1-2 yrs | I31: 11-20 members | J31: less than 1 ha | K31: Fresh vegetables | L31: No | M31: Direct selling, Trader | N31: Below 5,000 | O31: Yes | P31: Mobile data | Q31: No | S31: 5 | T31: 5 | U31: 5 | V31: 4 | W31: 4 | X31: 4 | Y31: 5 | Z31: 5 | AA31: 5 | AB31: 4 | AC31: 5 | AD31: 4 | AE31: 5 | AF31: 4 | AG31: 4 | AH31: 2 | AI31: 2 | AJ31: 2 | AK31: 2 | AL31: Tools, internet access, Training | AM31: Lack of tools/devices, and skills
A32: =A31+1 -> 31 | B32: Secretary | C32: 51 & above | D32: Female | E32: College Graduate | F32: 3-5 yrs | G32: San Vicente Farmers and Fisherfolks Association | H32: 3-5 yrs | I32: more than 30 | J32: less than 1 ha | K32: Fresh vegetables, Poultry | L32: No | M32: Trader, Direct selling, Online | N32: Above 20,000 | O32: Yes | P32: Both Mobile & WiFi | Q32: No | S32: 3 | T32: 3 | U32: 3 | V32: 3 | W32: 3 | X32: 4 | Y32: 4 | Z32: 4 | AA32: 4 | AB32: 3 | AC32: 3 | AD32: 4 | AE32: 4 | AF32: 4 | AG32: 4 | AH32: 3 | AI32: 4 | AJ32: 3 | AK32: 3 | AL32: Training | AM32: No formal training in digital marketing
A33: =A32+1 -> 32 | B33: Treasurer | C33: 51 & above | D33: Female | E33: High School Grad | F33: 1-2 yrs | G33: San Vicente Farmers and Fisherfolks Association | H33: 3-5 yrs | I33: more than 30 | J33: less than 1 ha | K33: Fresh vegetables, Poultry | L33: No | M33: Public market, Direct selling, Online | N33: Above 20,000 | O33: Yes | P33: Both Mobile & WiFi | Q33: No | S33: 4 | T33: 4 | U33: 4 | V33: 3 | W33: 3 | X33: 4 | Y33: 5 | Z33: 5 | AA33: 5 | AB33: 3 | AC33: 5 | AD33: 5 | AE33: 5 | AF33: 5 | AG33: 5 | AH33: 3 | AI33: 3 | AJ33: 2 | AK33: 2 | AL33: Training, Stable internet connection, tools | AM33: limited tools, unstable internet connection
A34: =A33+1 -> 33 | B34: Treasurer | C34: 18-30 | D34: Female | E34: High School Level | F34: less than 1 | G34: Blissful N' Abound Integrated Farmers Association | H34: 1-2 yrs | I34: 11-20 members | J34: less than 1 ha | K34: Fresh vegetables, Poultry | L34: No | M34: Public market, Direct selling, Online | N34: Above 20,000 | O34: Yes | P34: WiFi | Q34: No | S34: 3 | T34: 3 | U34: 4 | V34: 4 | W34: 4 | X34: 4 | Y34: 5 | Z34: 5 | AA34: 5 | AB34: 3 | AC34: 3 | AD34: 3 | AE34: 4 | AF34: 4 | AG34: 4 | AH34: 3 | AI34: 3 | AJ34: 3 | AK34: 2 | AL34: Training | AM34: Lack of digital marketing and content creation skills.
A35: =A34+1 -> 34 | B35: Business Manager | C35: 31-40 | D35: Male | E35: High School Grad | F35: less than 1 | G35: Blissful N' Abound Integrated Farmers Association | H35: 1-2 yrs | I35: 11-20 members | J35: less than 1 ha | K35: Fresh vegetables, Poultry | L35: No | M35: Public market, Direct selling, Online | N35: Above 20,000 | O35: Yes | P35: WiFi | Q35: No | S35: 4 | T35: 4 | U35: 3 | V35: 5 | W35: 5 | X35: 4 | Y35: 5 | Z35: 5 | AA35: 5 | AB35: 3 | AC35: 3 | AD35: 3 | AE35: 4 | AF35: 4 | AG35: 4 | AH35: 2 | AI35: 3 | AJ35: 3 | AK35: 2 | AL35: Training | AM35: Lack of basic digital skills.
A36: =A35+1 -> 35 | B36: President | C36: 41-50 | D36: Male | E36: College Graduate | F36: 1-2 yrs | G36: District 4 Rice, Coconut and Banana Farmers Association | H36: 1-2 yrs | I36: 21-30 members | J36: less than 1 ha | K36: Fresh vegetables, Poultry | L36: No | M36: Trader, Direct, Institutional buyer | N36: Above 20,000 | O36: Yes | P36: Mobile data | Q36: No | S36: 4 | T36: 4 | U36: 4 | V36: 3 | W36: 4 | X36: 4 | Y36: 4 | Z36: 4 | AA36: 4 | AB36: 3 | AC36: 4 | AD36: 4 | AE36: 4 | AF36: 4 | AG36: 4 | AH36: 1 | AI36: 2 | AJ36: 2 | AK36: 1 | AL36: Training, Stable internet connection, tools | AM36: Not using digital marketing yet.
A37: =A36+1 -> 36 | B37: Business Manager | C37: 41-50 | D37: Female | E37: High School Level | F37: 1-2 yrs | G37: District 4 Rice, Coconut and Banana Farmers Association | H37: 1-2 yrs | I37: 21-30 members | J37: less than 1 ha | K37: Fresh vegetables, Poultry | L37: No | M37: Trader, Direct, Institutional buyer | N37: Above 20,000 | O37: Yes | P37: Mobile data | Q37: No | S37: 4 | T37: 5 | U37: 5 | V37: 4 | W37: 4 | X37: 5 | Y37: 4 | Z37: 4 | AA37: 5 | AB37: 3 | AC37: 4 | AD37: 4 | AE37: 4 | AF37: 4 | AG37: 4 | AH37: 2 | AI37: 3 | AJ37: 2 | AK37: 1 | AL37: Training, Stable internet connection, tools | AM37: Not using digital marketing yet.
A38: =A37+1 -> 37 | B38: Treasurer | C38: 41-50 | D38: Female | E38: High School Grad | F38: 3-5 yrs | G38: Lamaca Farmers Association | H38: 3-5 yrs | I38: 21-30 members | J38: 1-2 ha | K38: Fresh vegetables, Poultry | L38: No | M38: Public market, Direct selling | N38: Above 20,000 | O38: Yes | P38: Both Mobile & WiFi | Q38: No | S38: 4 | T38: 4 | U38: 4 | V38: 3 | W38: 3 | X38: 3 | Y38: 3 | Z38: 4 | AA38: 4 | AB38: 3 | AC38: 4 | AD38: 4 | AE38: 3 | AF38: 4 | AG38: 4 | AH38: 2 | AI38: 3 | AJ38: 2 | AK38: 2 | AL38: Training, tools | AM38: unstable internet connection
A39: =A38+1 -> 38 | B39: Secretary | C39: 41-50 | D39: Female | E39: College Grad | F39: 3-5 yrs | G39: Lamaca Farmers Association | H39: 3-5 yrs | I39: 21-30 members | J39: 1-2 ha | K39: Fresh vegetables, Poultry | L39: No | M39: Public market, Direct selling | N39: Above 20,000 | O39: Yes | P39: Both Mobile & WiFi | Q39: No | S39: 4 | T39: 3 | U39: 3 | V39: 3 | W39: 3 | X39: 3 | Y39: 4 | Z39: 4 | AA39: 4 | AB39: 4 | AC39: 3 | AD39: 3 | AE39: 3 | AF39: 3 | AG39: 3 | AH39: 2 | AI39: 3 | AJ39: 2 | AK39: 2 | AL39: Training, stable internet connection | AM39: Limited skills, time, budget, and manpower, lack of strategy
... A41: =A40+1 -> 40 | B41: Treasurer | C41: 41-50 | D41: Female | E41: College Level | F41: 3-5 yrs | G41: San Roque Farmers and Fisherfolks Association | H41: 3-5 yrs | I41: 21-30 members | J41: less than 1 ha | K41: Poultry | L41: No | M41: Trader, Direct selling | N41: Above 20,000 | O41: Yes | P41: Both Mobile & WiFi | Q41: No | S41: 4 | T41: 3 | U41: 3 | V41: 4 | W41: 4 | X41: 4 | Y41: 4 | Z41: 4 | AA41: 3 | AB41: 3 | AC41: 5 | AD41: 3 | AE41: 3 | AF41: 3 | AG41: 3 | AH41: 1 | AI41: 2 | AJ41: 1 | AK41: 1 | AL41: Training, stable internet connection | AM41: Not using digital marketing yet.
A42: =A41+1 -> 41 | B42: Treasurer | C42: 31-40 | D42: Female | E42: High School Grad | F42: 3-5 yrs | G42: Calintaan Farmers Association | H42: 3-5 yrs | I42: 21-30 members | J42: less than 1 ha | K42: Poultry | L42: No | M42: Trader, Direct Selling, Institutional buyer | N42: Above 20,000 | O42: Yes | P42: Mobile data | Q42: Yes | R42: Posting products on social media | S42: 5 | T42: 4 | U42: 4 | V42: 3 | W42: 3 | X42: 4 | Y42: 4 | Z42: 3 | AA42: 4 | AB42: 4 | AC42: 3 | AD42: 3 | AE42: 3 | AF42: 3 | AG42: 3 | AH42: 2 | AI42: 4 | AJ42: 2 | AK42: 2 | AL42: stable internet connection, additional Training | AM42: unstable internet connection
A43: =A42+1 -> 42 | B43: Secretary | C43: 31-40 | D43: Female | E43: High School Grad | F43: 3-5 yrs | G43: Calintaan Farmers Association | H43: 3-5 ys | I43: 21-30 members | J43: less than 1 ha | K43: Poultry | L43: No | M43: Trader, Direct Selling, Institutional buyer | N43: Above 20,000 | O43: Yes | P43: Mobile data | Q43: Yes | R43: Posting products on social media | S43: 5 | T43: 4 | U43: 4 | V43: 3 | W43: 4 | X43: 4 | Y43: 4 | Z43: 4 | AA43: 4 | AB43: 3 | AC43: 3 | AD43: 3 | AE43: 3 | AF43: 3 | AG43: 3 | AH43: 3 | AI43: 4 | AJ43: 3 | AK43: 3 | AL43: stable internet connection, additional Training | AM43: unstable internet connection
A44: =A43+1 -> 43 | B44: President | C44: 41-50 | D44: Female | E44: High School Grad | F44: 3-5 yrs | G44: Barangay Dayanog Small Coconut Farmers and Fisherfolks Association | H44: 3-5 yrs | I44: 11-20 members | J44: less than 1 ha | K44: Fresh vegetables | L44: No | M44: Trader, Direct selling | N44: Above 20,000 | O44: Yes | P44: Mobile data | Q44: No | S44: 5 | T44: 5 | U44: 4 | V44: 4 | W44: 4 | X44: 4 | Y44: 5 | Z44: 5 | AA44: 4 | AB44: 3 | AC44: 4 | AD44: 4 | AE44: 4 | AF44: 3 | AG44: 4 | AH44: 1 | AI44: 2 | AJ44: 1 | AK44: 1 | AL44: Training, stable internet connection | AM44: limited digital tools and skills, unstable internet connection
A45: =A44+1 -> 44 | B45: Secretary | C45: 41-50 | D45: Female | E45: High School Level | F45: 3-5 yrs | G45: Barangay Dayanog Small Coconut Farmers and Fisherfolks Association | H45: 3-5 yrs | I45: 11-20 members | J45: less than 1 ha | K45: Fresh vegetables | L45: No | M45: Trader, Direct selling | N45: Above 20,000 | O45: Yes | P45: Mobile data | Q45: No | S45: 5 | T45: 5 | U45: 4 | V45: 4 | W45: 4 | X45: 5 | Y45: 5 | Z45: 5 | AA45: 5 | AB45: 4 | AC45: 4 | AD45: 4 | AE45: 5 | AF45: 3 | AG45: 4 | AH45: 1 | AI45: 2 | AJ45: 1 | AK45: 1 | AL45: Training, stable internet connection | AM45: limited digital tools and skills, unstable internet connection
A46: =A45+1 -> 45 | B46: President | C46: 41-50 | D46: Male | E46: High School Graduate | F46: 1-2 yrs | G46: PUNDOK MAAMUMAHON | H46: 1-2 yrs | I46: more than 30 | J46: 1-2 ha | K46: Fresh vegetables, Poultry | L46: No | M46: Public market, Trader,Direct selling | N46: Above 20,000 | O46: Yes | P46: Both Mobile & WiFi | Q46: No | S46: 4 | T46: 3 | U46: 3 | V46: 3 | W46: 3 | X46: 4 | Y46: 4 | Z46: 4 | AA46: 4 | AB46: 3 | AC46: 4 | AD46: 3 | AE46: 4 | AF46: 3 | AG46: 4 | AH46: 1 | AI46: 3 | AJ46: 2 | AK46: 1 | AL46: Training | AM46: Limited skills and manpower
A47: =A46+1 -> 46 | B47: Member | C47: 41-50 | D47: Male | E47: College Graduate | F47: 1-2 yrs | G47: PUNDOK MAAMUMAHON | H47: 1-2 yrs | I47: more than 30 | J47: 1-2 ha | K47: Fresh vegetables, Poultry | L47: No | M47: Public market, Trader,Direct selling | N47: Above 20,000 | O47: Yes | P47: Both Mobile & WiFi | Q47: No | S47: 3 | T47: 3 | U47: 3 | V47: 3 | W47: 3 | X47: 4 | Y47: 4 | Z47: 4 | AA47: 4 | AB47: 3 | AC47: 3 | AD47: 3 | AE47: 4 | AF47: 4 | AG47: 4 | AH47: 2 | AI47: 4 | AJ47: 3 | AK47: 2 | AL47: Training | AM47: Limited time and skills for creating content
A48: =A47+1 -> 47 | B48: President | C48: 51 & above | D48: Male | E48: High School Level | F48: 1-2 yrs | G48: Coot-Dinahugan Integrated Farming Association | H48: 1-2 yrs | I48: 21-30 members | J48: less than 1 ha | K48: Livestock | L48: No | M48: Trader, Direct selling | N48: Above 20,000 | O48: Yes | P48: Mobile data | Q48: No | S48: 5 | T48: 5 | U48: 5 | V48: 4 | W48: 4 | X48: 5 | Y48: 4 | Z48: 5 | AA48: 5 | AB48: 3 | AC48: 4 | AD48: 3 | AE48: 4 | AF48: 3 | AG48: 4 | AH48: 1 | AI48: 1 | AJ48: 1 | AK48: 1 | AL48: Training, tools, stable internet connection | AM48: limited tools/ devices and internet access
A49: =A48+1 -> 48 | B49: Secretary | C49: 41-50 | D49: Female | E49: High school Graduate | F49: 1-2 yrs | G49: Coot-Dinahugan Integrated Farming Association | H49: 1-2 yrs | I49: 21-30 members | J49: less than 1 ha | K49: Livestock | L49: No | M49: Trader, Direct selling | N49: Above 20,000 | O49: Yes | P49: Mobile data | Q49: No | S49: 5 | T49: 4 | U49: 4 | V49: 4 | W49: 4 | X49: 5 | Y49: 4 | Z49: 5 | AA49: 4 | AB49: 3 | AC49: 4 | AD49: 3 | AE49: 4 | AF49: 3 | AG49: 3 | AH49: 1 | AI49: 1 | AJ49: 1 | AK49: 1 | AL49: Training, tools, stable internet connection | AM49: limited tools/ devices and internet access
A50: =A49+1 -> 49 | B50: Business Manager | C50: 41-50 | D50: Male | E50: College Graduate | F50: 3-5 yrs | G50: Magallanes Farmers Association | H50: 3-5 yrs | I50: 11-20 members | J50: less than 1 ha | K50: Livestock, Poultry | L50: No | M50: Direct selling, Institutional buyer | N50: Above 20,000 | O50: Yes | P50: Both Mobile & WiFi | Q50: No | S50: 4 | T50: 4 | U50: 4 | V50: 3 | W50: 3 | X50: 3 | Y50: 4 | Z50: 3 | AA50: 4 | AB50: 3 | AC50: 3 | AD50: 3 | AE50: 4 | AF50: 4 | AG50: 4 | AH50: 2 | AI50: 3 | AJ50: 2 | AK50: 2 | AL50: Training | AM50: limited skills
A51: =A50+1 -> 50 | B51: President | C51: 51 & above | D51: Male | E51: College level | F51: 3-5 yrs | G51: Magallanes Farmers Association | H51: 3-5 yrs | I51: 11-20 members | J51: less than 1 ha | K51: Livestock, Poultry | L51: No | M51: Direct selling, Institutional buyer, online | N51: Above 20,000 | O51: Yes | P51: Both Mobile & WiFi | Q51: No | S51: 5 | T51: 4 | U51: 3 | V51: 3 | W51: 4 | X51: 4 | Y51: 3 | Z51: 3 | AA51: 5 | AB51: 4 | AC51: 3 | AD51: 3 | AE51: 3 | AF51: 4 | AG51: 3 | AH51: 3 | AI51: 3 | AJ51: 3 | AK51: 3 | AL51: Training, stable internet connection | AM51: limited skills and tools
A52: =A51+1 -> 51 | B52: President | C52: 51 & above | D52: Female | E52: College Graduate | F52: 3-5 yrs | G52: Pinamudlan Women's Association | H52: 3-5 yrs | I52: 11-20 members | J52: less than 1 ha | K52: livestock | L52: No | M52: Institutional buyer, direct selling | N52: Above 20,000 | O52: Oo | P52: Mobile data | Q52: Yes | R52: Posting products on social media | S52: 5 | T52: 4 | U52: 5 | V52: 4 | W52: 4 | X52: 4 | Y52: 4 | Z52: 4 | AA52: 4 | AB52: 4 | AC52: 4 | AD52: 4 | AE52: 3 | AF52: 3 | AG52: 3 | AH52: 2 | AI52: 2 | AJ52: 2 | AK52: 2 | AL52: Tools/devices, stable internet connection | AM52: unstable internet connection
A53: =A52+1 -> 52 | B53: Secretary | C53: 41-50 | D53: Female | E53: High School level | F53: 3-5 yrs | G53: Pinamudlan Women's Association | H53: 3-5 yrs | I53: 11-20 members | J53: less than 1 ha | K53: livestock | L53: No | M53: Institutional buyer, direct selling | N53: Above 20,000 | O53: Oo | P53: Mobile data | Q53: Yes | R53: Posting products on social media | S53: 5 | T53: 4 | U53: 4 | V53: 4 | W53: 4 | X53: 4 | Y53: 5 | Z53: 5 | AA53: 5 | AB53: 4 | AC53: 4 | AD53: 4 | AE53: 3 | AF53: 3 | AG53: 3 | AH53: 2 | AI53: 3 | AJ53: 2 | AK53: 2 | AL53: Tools/devices, stable internet connection | AM53: unstable internet connection
A54: =A53+1 -> 53 | B54: President | C54: 51 & above | D54: Female | E54: High School Grad | F54: 3-5 yrs | G54: Maalagaron Abtik Responsable Ug Ehemplo Nga Mga Kababayen-An (MARE) CARES sa Hinapo Women’s Association | H54: 3-5 yrs | I54: 11-20 members | J54: less than 1 ha | K54: Poultry | L54: No | M54: Trader, Direct selling | N54: Above 20,000 | O54: Oo | P54: WiFi | Q54: No | S54: 4 | T54: 4 | U54: 4 | V54: 4 | W54: 4 | X54: 5 | Y54: 5 | Z54: 5 | AA54: 5 | AB54: 3 | AC54: 3 | AD54: 3 | AE54: 4 | AF54: 4 | AG54: 4 | AH54: 2 | AI54: 3 | AJ54: 2 | AK54: 2 | AL54: training, tools/devices, stable internet connection | AM54: lack of skills/experience, budget, tools, and stable internet connection
A55: =A54+1 -> 54 | B55: Business Manager | C55: 41-50 | D55: Female | E55: High School Grad | F55: 3-5 yrs | G55: Maalagaron Abtik Responsable Ug Ehemplo Nga Mga Kababayen-An (MARE) CARES sa Hinapo Women’s Association | H55: 3-5 yrs | I55: 11-20 members | J55: less than 1 ha | K55: Poultry | L55: No | M55: Trader, Direct selling | N55: Above 20,000 | O55: Oo | P55: WiFi | Q55: No | S55: 5 | T55: 4 | U55: 4 | V55: 4 | W55: 4 | X55: 4 | Y55: 4 | Z55: 5 | AA55: 4 | AB55: 4 | AC55: 3 | AD55: 3 | AE55: 4 | AF55: 3 | AG55: 4 | AH55: 1 | AI55: 4 | AJ55: 2 | AK55: 1 | AL55: training, tools/devices, stable internet connection | AM55: lack of skills/experience, budget, tools, and stable internet connection
A56: =A55+1 -> 55 | B56: President | C56: 41-50 | D56: Male | E56: College Graduate | F56: 1-2 yrs | G56: Cabulisan Farmers Association | H56: 1-2 yrs | I56: 21-30 members | J56: less than 1 ha | K56: Poultry | L56: No | M56: Trader, Direct selling, Institutional buyer | N56: Above 20,000 | O56: Yes | P56: Both Mobile & WiFi | Q56: No | S56: 4 | T56: 3 | U56: 3 | V56: 4 | W56: 4 | X56: 5 | Y56: 4 | Z56: 5 | AA56: 4 | AB56: 3 | AC56: 3 | AD56: 3 | AE56: 4 | AF56: 3 | AG56: 4 | AH56: 2 | AI56: 4 | AJ56: 3 | AK56: 2 | AL56: training, tools | AM56: limited skills in content creation
A57: =A56+1 -> 56 | B57: Secretary | C57: 31-40 | D57: Female | E57: High School Grad | F57: 1-2 yrs | G57: Cabulisan Farmers Association | H57: 1-2 yrs | I57: 21-30 members | J57: less than 1 ha | K57: Poultry | L57: No | M57: Trader, Direct selling, Institutional buyer | N57: Above 20,000 | O57: Yes | P57: Both Mobile & WiFi | Q57: No | S57: 4 | T57: 4 | U57: 4 | V57: 4 | W57: 5 | X57: 4 | Y57: 4 | Z57: 5 | AA57: 5 | AB57: 3 | AC57: 3 | AD57: 3 | AE57: 4 | AF57: 4 | AG57: 4 | AH57: 1 | AI57: 3 | AJ57: 2 | AK57: 1 | AL57: training, tools | AM57: Limited time and skills for creating content
A58: =A57+1 -> 57 | B58: President | C58: 51 & above | D58: Female | E58: High School Graduate | F58: 1-2 yrs | G58: Talisay Women's Association | H58: 1-2 yrs | I58: 21-30 members | J58: less than 1 ha | K58: Poultry | L58: No | M58: Trader, Direct selling | N58: Above 20,000 | O58: Yes | P58: Mobile data | Q58: No | S58: 5 | T58: 4 | U58: 5 | V58: 4 | W58: 3 | X58: 5 | Y58: 4 | Z58: 5 | AA58: 4 | AB58: 3 | AC58: 3 | AD58: 3 | AE58: 3 | AF58: 3 | AG58: 4 | AH58: 1 | AI58: 3 | AJ58: 2 | AK58: 1 | AL58: training, tools | AM58: unstable internet connection
A59: =A58+1 -> 58 | B59: BOD | C59: 51 & above | D59: Female | E59: High School Graduate | F59: 1-2 yrs | G59: Talisay Women's Association | H59: 1-2 yrs | I59: 21-30 members | J59: less than 1 ha | K59: Poultry | L59: No | M59: Trader, Direct selling | N59: Above 20,000 | O59: Yes | P59: Mobile data | Q59: No | S59: 5 | T59: 5 | U59: 5 | V59: 4 | W59: 4 | X59: 4 | Y59: 5 | Z59: 5 | AA59: 5 | AB59: 3 | AC59: 3 | AD59: 3 | AE59: 4 | AF59: 3 | AG59: 4 | AH59: 2 | AI59: 4 | AJ59: 2 | AK59: 2 | AL59: training, stable internet connection | AM59: Unstable internet connection
A60: =A59+1 -> 59 | B60: President | C60: 31-40 | D60: Male | E60: College Level | F60: 1-2 yrs | G60: Sabang II Rural Improvement Club | H60: 1-2 yrs | I60: 21-30 members | J60: less than 1 ha | K60: Poultry | L60: No | M60: Direct Selling, Institutional buyer | N60: Above 20,000 | O60: Yes | P60: Both Mobile & WiFi | Q60: No | S60: 3 | T60: 4 | U60: 3 | V60: 3 | W60: 3 | X60: 4 | Y60: 3 | Z60: 4 | AA60: 3 | AB60: 2 | AC60: 3 | AD60: 3 | AE60: 3 | AF60: 3 | AG60: 4 | AH60: 3 | AI60: 4 | AJ60: 3 | AK60: 3 | AL60: training | AM60: lack of consistency in creating content
A61: =A60+1 -> 60 | B61: Treasurer | C61: 31-40 | D61: Female | E61: High School Grad | F61: 1-2 yrs | G61: Sabang II Rural Improvement Club | H61: 1-2 yrs | I61: 21-30 members | J61: less than 1 ha | K61: Poultry | L61: No | M61: Direct Selling, Institutional buyer | N61: Above 20,000 | O61: Yes | P61: Both Mobile & WiFi | Q61: No | S61: 4 | T61: 3 | U61: 3 | V61: 3 | W61: 4 | X61: 4 | Y61: 4 | Z61: 5 | AA61: 4 | AB61: 3 | AC61: 4 | AD61: 3 | AE61: 4 | AF61: 3 | AG61: 4 | AH61: 3 | AI61: 4 | AJ61: 3 | AK61: 3 | AL61: training | AM61: transportation for product delivery
A62: =A61+1 -> 61 | B62: President | C62: 51 & above | D62: Male | E62: High School Level | F62: 1-2 yrs | G62: Aguada Fisherfolks Mangrove Kinis and Bangus Sustainable Association | H62: 1-2 yrs | I62: 11-20 members | J62: less than 1 ha | K62: Poultry | L62: No | M62: Trader, Direct selling | N62: Above 20,000 | O62: Yes | P62: Both Mobile & WiFi | Q62: No | S62: 4 | T62: 5 | U62: 4 | V62: 4 | W62: 4 | X62: 5 | Y62: 4 | Z62: 5 | AA62: 4 | AB62: 3 | AC62: 4 | AD62: 3 | AE62: 5 | AF62: 4 | AG62: 5 | AH62: 2 | AI62: 3 | AJ62: 2 | AK62: 2 | AL62: Training | AM62: Limited digital skills
A63: =A62+1 -> 62 | B63: Treasurer | C63: 41-50 | D63: Female | E63: High School Grad | F63: 1-2 yrs | G63: Aguada Fisherfolks Mangrove Kinis and Bangus Sustainable Association | H63: 1-2 yrs | I63: 11-20 members | J63: less than 1 ha | K63: Poultry | L63: No | M63: Trader, Direct selling | N63: Above 20,000 | O63: Yes | P63: Both Mobile & WiFi | Q63: No | S63: 5 | T63: 4 | U63: 4 | V63: 4 | W63: 4 | X63: 4 | Y63: 4 | Z63: 5 | AA63: 5 | AB63: 4 | AC63: 3 | AD63: 3 | AE63: 5 | AF63: 4 | AG63: 5 | AH63: 2 | AI63: 4 | AJ63: 2 | AK63: 2 | AL63: Training | AM63: Limited digital skills
A64: =A63+1 -> 63 | B64: President | C64: 41-50 | D64: Female | E64: High School Level | F64: 1-2 yrs | G64: Magsasakang Masisipag ng Mapanas (3M) Association | H64: 1-2 yrs | I64: 21-30 members | J64: 1-2 ha | K64: Fresh vegetables, Corn | L64: No | M64: Trader, Direct selling, Online | N64: 10,001 - 20,000 | O64: Yes | P64: Both Mobile & WiFi | Q64: No | S64: 4 | T64: 4 | U64: 4 | V64: 3 | W64: 3 | X64: 4 | Y64: 4 | Z64: 5 | AA64: 5 | AB64: 3 | AC64: 3 | AD64: 3 | AE64: 3 | AF64: 3 | AG64: 4 | AH64: 3 | AI64: 3 | AJ64: 2 | AK64: 2 | AL64: Training | AM64: limited skills in content creation
A65: =A64+1 -> 64 | B65: Treasurer | C65: 41-50 | D65: Female | E65: High School Grad | F65: 1-2 yrs | G65: Magsasakang Masisipag ng Mapanas (3M) Association | H65: 1-2 yrs | I65: 21-30 members | J65: 1-2 ha | K65: Fresh vegetables, Corn | L65: No | M65: Trader, Direct selling, Online | N65: 10,001 - 20,000 | O65: Yes | P65: Both Mobile & WiFi | Q65: No | S65: 5 | T65: 4 | U65: 4 | V65: 4 | W65: 4 | X65: 5 | Y65: 5 | Z65: 5 | AA65: 5 | AB65: 4 | AC65: 3 | AD65: 4 | AE65: 5 | AF65: 4 | AG65: 5 | AH65: 3 | AI65: 3 | AJ65: 2 | AK65: 3 | AL65: Training, tools | AM65: Lack of tools for product photography
... A79: =A78+1 -> 78 | B79: Member | C79: 41-50 | D79: Female | E79: High School Grad | F79: 1-2 yrs | G79: Manraya Fisherfolks and Farmers Association | H79: 1-2 yrs | I79: 21-30 members | J79: less than 1 ha | K79: Livestock | L79: No | M79: Direct selling | N79: Above 20,000 | O79: Yes | P79: Mobile data | Q79: No | S79: 4 | T79: 4 | U79: 4 | V79: 3 | W79: 3 | X79: 4 | Y79: 4 | Z79: 4 | AA79: 4 | AB79: 3 | AC79: 3 | AD79: 3 | AE79: 5 | AF79: 3 | AG79: 3 | AH79: 3 | AI79: 3 | AJ79: 3 | AK79: 3 | AL79: Training, internet connection, tools | AM79: limited skills, unstable internet connection
A80: =A79+1 -> 79 | B80: President | C80: 51 & above | D80: Male | E80: High School Graduate | F80: 3-5 yrs | G80: Bolusao Coconut Based Integrated FA | H80: 3-5 yrs | I80: 11-20 members | J80: 1-2 ha | K80: Poultry, Processed products | L80: Yes; Tablea, Chocolate, sandwich spread | M80: Trader, Direct selling, online | N80: Above 20,000 | O80: Yes | P80: Both Mobile & WiFi | Q80: Yes | R80: Posting products on social media | S80: 3 | T80: 3 | U80: 3 | V80: 3 | W80: 3 | X80: 3 | Y80: 4 | Z80: 4 | AA80: 4 | AB80: 3 | AC80: 3 | AD80: 3 | AE80: 5 | AF80: 3 | AG80: 3 | AH80: 3 | AI80: 4 | AJ80: 3 | AK80: 3 | AL80: Additional training, stable internet connection | AM80: lack of strategy
A81: =A80+1 -> 80 | B81: Member | C81: 41-50 | D81: Male | E81: College Graduate | F81: 3-5 yrs | G81: Bolusao Coconut Based Integrated FA | H81: 3-5 yrs | I81: 11-20 members | J81: 1-2 ha | K81: Poultry, Processed products | L81: Yes; Tablea, Chocolate, sandwich spread | M81: Trader, Direct selling, online | N81: Above 20,000 | O81: Yes | P81: Both Mobile & WiFi | Q81: Yes | R81: Posting products on social media | S81: 3 | T81: 3 | U81: 3 | V81: 3 | W81: 3 | X81: 4 | Y81: 4 | Z81: 4 | AA81: 4 | AB81: 3 | AC81: 3 | AD81: 3 | AE81: 4 | AF81: 4 | AG81: 4 | AH81: 2 | AI81: 4 | AJ81: 3 | AK81: 2 | AL81: Additional training, stable internet connection | AM81: lack of strategy
A82: =A81+1 -> 81 | B82: President | C82: 41-50 | D82: Female | E82: College Graduate | F82: 3-5 yrs | G82: San Isidro Women's Association | H82: 3-5 yrs | I82: 11-20 members | J82: 1-2 ha | K82: Fresh vegetables, Poultry, Processed products | L82: Yes; Cassava cake | M82: Trader, Direct selling, Institutional buyer, Online | N82: Above 20,000 | O82: Yes | P82: Both Mobile & WiFi | Q82: No | S82: 4 | T82: 3 | U82: 3 | V82: 3 | W82: 3 | X82: 4 | Y82: 4 | Z82: 4 | AA82: 3 | AB82: 3 | AC82: 4 | AD82: 3 | AE82: 5 | AF82: 5 | AG82: 5 | AH82: 3 | AI82: 4 | AJ82: 3 | AK82: 3 | AL82: Training, tools, stable internet connection | AM82: limited skills and usage of digital marketing
A83: =A82+1 -> 82 | B83: Secretary | C83: 41-50 | D83: Female | E83: High School Grad | F83: 3-5 yrs | G83: San Isidro Women's Association | H83: 3-5 yrs | I83: 11-20 members | J83: 1-2 ha | K83: Fresh vegetables, Poultry, Processed products | L83: Yes; Cassava cake | M83: Trader, Direct selling, Institutional buyer, Online | N83: Above 20,000 | O83: Yes | P83: Both Mobile & WiFi | Q83: No | S83: 4 | T83: 3 | U83: 4 | V83: 3 | W83: 3 | X83: 4 | Y83: 4 | Z83: 4 | AA83: 4 | AB83: 4 | AC83: 3 | AD83: 3 | AE83: 4 | AF83: 4 | AG83: 5 | AH83: 3 | AI83: 3 | AJ83: 3 | AK83: 3 | AL83: Training, tools, stable internet connection | AM83: limited skills, unstable internet connection
A84: =A83+1 -> 83 | B84: President | C84: 41-50 | D84: Female | E84: High School Level | F84: 1-2 yrs | G84: Sagkaray Farmers and Development Association | H84: 1-2 yrs | I84: 11-20 members | J84: 1-2 ha | K84: Fresh vegetables, processed products | L84: Yes; tablea | M84: Trader, Direct selling, Institutional buyer, Online | N84: 5,001 - 10,000 | O84: Yes | P84: Mobile data | Q84: No | S84: 3 | T84: 3 | U84: 3 | V84: 3 | W84: 3 | X84: 4 | Y84: 4 | Z84: 4 | AA84: 4 | AB84: 3 | AC84: 3 | AD84: 3 | AE84: 4 | AF84: 4 | AG84: 4 | AH84: 2 | AI84: 4 | AJ84: 3 | AK84: 2 | AL84: Training, tools, stable internet connection | AM84: limited skills, unstable internet connection
A85: =A84+1 -> 84 | B85: Treasurer | C85: 41-50 | D85: Female | E85: High School Level | F85: 1-2 yrs | G85: Sagkaray Farmers and Development Association | H85: 1-2 yrs | I85: 11-20 members | J85: 1-2 ha | K85: Fresh vegetables, processed products | L85: Yes; tablea | M85: Trader, Direct selling, Institutional buyer, Online | N85: 5,001 - 10,000 | O85: Yes | P85: Mobile data | Q85: No | S85: 5 | T85: 4 | U85: 5 | V85: 3 | W85: 3 | X85: 3 | Y85: 5 | Z85: 3 | AA85: 3 | AB85: 3 | AC85: 3 | AD85: 3 | AE85: 3 | AF85: 3 | AG85: 3 | AH85: 2 | AI85: 3 | AJ85: 2 | AK85: 2 | AL85: Training, tools/devices | AM85: limited skills
A86: =A85+1 -> 85 | B86: President | C86: 41-50 | D86: Male | E86: High School Grad | F86: 1-2 yrs | G86: Tanglad Farmers Association | H86: 1-2 yrs | I86: 11-20 members | J86: 1-2 ha | K86: Fresh vegetables, Poultry | L86: No | M86: Trader, Direct selling | N86: Above 20,000 | O86: Yes | P86: Mobile data | Q86: No | S86: 5 | T86: 5 | U86: 5 | V86: 4 | W86: 3 | X86: 4 | Y86: 4 | Z86: 4 | AA86: 4 | AB86: 4 | AC86: 3 | AD86: 3 | AE86: 4 | AF86: 3 | AG86: 4 | AH86: 3 | AI86: 2 | AJ86: 2 | AK86: 2 | AL86: Training, tools/devices | AM86: limited skills
A87: =A86+1 -> 86 | B87: Secretary | C87: 31-40 | D87: Female | E87: High School Grad | F87: 1-2 yrs | G87: Tanglad Farmers Association | H87: 1-2 yrs | I87: 11-20 members | J87: 1-2 ha | K87: Fresh vegetables, Poultry | L87: No | M87: Trader, Direct selling | N87: Above 20,000 | O87: Yes | P87: Mobile data | Q87: No | S87: 4 | T87: 4 | U87: 4 | V87: 3 | W87: 3 | X87: 4 | Y87: 4 | Z87: 4 | AA87: 4 | AB87: 3 | AC87: 3 | AD87: 3 | AE87: 5 | AF87: 3 | AG87: 3 | AH87: 3 | AI87: 3 | AJ87: 3 | AK87: 3 | AL87: tools/ device | AM87: limited tools/ gadgets
A88: =A87+1 -> 87 | B88: President | C88: 41-50 | D88: Male | E88: High School Level | F88: 1-2 yrs | G88: Buyayawon Farmers Association | H88: 1-2 yrs | I88: 11-20 members | J88: less than 1 ha | K88: Poultry | L88: No | M88: Direct selling, Instituional buyer, online | N88: Above 20,000 | O88: Yes | P88: Mobile data | Q88: No | S88: 3 | T88: 3 | U88: 3 | V88: 3 | W88: 3 | X88: 3 | Y88: 4 | Z88: 4 | AA88: 4 | AB88: 3 | AC88: 3 | AD88: 3 | AE88: 5 | AF88: 3 | AG88: 3 | AH88: 3 | AI88: 4 | AJ88: 3 | AK88: 3 | AL88: tools/ device | AM88: limited tools/ gadgets
A89: =A88+1 -> 88 | B89: Treasurer | C89: 41-50 | D89: Female | E89: High School Grad | F89: 1-2 yrs | G89: Buyayawon Farmers Association | H89: 1-2 yrs | I89: 11-20 members | J89: less than 1 ha | K89: Poultry | L89: No | M89: Direct selling, Instituional buyer, online | N89: Above 20,000 | O89: Yes | P89: Mobile data | Q89: No | S89: 4 | T89: 3 | U89: 3 | V89: 3 | W89: 3 | X89: 5 | Y89: 3 | Z89: 5 | AA89: 4 | AB89: 3 | AC89: 5 | AD89: 4 | AE89: 4 | AF89: 3 | AG89: 4 | AH89: 2 | AI89: 3 | AJ89: 2 | AK89: 2 | AL89: tools/ device | AM89: limited tools/ gadgets
A90: =A89+1 -> 89 | B90: President | C90: 51 & above | D90: Male | E90: High School Level | F90: 1-2 yrs | G90: Bangon-Alugan-Tanauan-Sta. Cruz Corn and Cassava FA | H90: 1-2 yrs | I90: 21-30 members | J90: less than 1 ha | K90: Poultry | L90: No | M90: Direct selling, Instituional buyer, online | N90: Above 20,000 | O90: Yes | P90: Mobile data | Q90: No | S90: 4 | T90: 3 | U90: 3 | V90: 4 | W90: 4 | X90: 4 | Y90: 4 | Z90: 4 | AA90: 3 | AB90: 3 | AC90: 5 | AD90: 3 | AE90: 3 | AF90: 3 | AG90: 3 | AH90: 1 | AI90: 2 | AJ90: 1 | AK90: 1 | AL90: Training, tools/devices | AM90: limited skills
A91: =A90+1 -> 90 | B91: Treasurer | C91: 41-50 | D91: Female | E91: High School Level | F91: 1-2 yrs | G91: Bangon-Alugan-Tanauan-Sta. Cruz Corn and Cassava FA | H91: 1-2 yrs | I91: 21-30 members | J91: less than 1 ha | K91: Poultry | L91: No | M91: Direct selling, Instituional buyer, online | N91: Above 20,000 | O91: Yes | P91: Mobile data | Q91: No | S91: 5 | T91: 4 | U91: 4 | V91: 3 | W91: 3 | X91: 4 | Y91: 4 | Z91: 3 | AA91: 4 | AB91: 4 | AC91: 3 | AD91: 3 | AE91: 3 | AF91: 3 | AG91: 3 | AH91: 2 | AI91: 4 | AJ91: 2 | AK91: 2 | AL91: Training, tools/devices | AM91: limited skills
A92: =A91+1 -> 91 | B92: President | C92: 41-50 | D92: Female | E92: Elementary Level | F92: 3-5 yrs | G92: Mabuhay Farmers Peace Builders and Development Association | H92: 3-5 yrs | I92: 21-30 members | J92: less than 1 ha | K92: Poultry | L92: No | M92: Trader, Direct selling | N92: Above 20,000 | O92: Yes | P92: WiFi | Q92: No | S92: 5 | T92: 4 | U92: 4 | V92: 3 | W92: 3 | X92: 4 | Y92: 5 | Z92: 5 | AA92: 4 | AB92: 5 | AC92: 5 | AD92: 5 | AE92: 4 | AF92: 3 | AG92: 4 | AH92: 2 | AI92: 3 | AJ92: 2 | AK92: 2 | AL92: Tools, stable internet connection | AM92: limited digital skills
A93: =A92+1 -> 92 | B93: Business Manager | C93: 41-50 | D93: Male | E93: High School Level | F93: 3-5 yrs | G93: Mabuhay Farmers Peace Builders and Development Association | H93: 3-5 yrs | I93: 21-30 members | J93: less than 1 ha | K93: Poultry | L93: No | M93: Trader, Direct selling | N93: Above 20,000 | O93: Yes | P93: WiFi | Q93: No | S93: 5 | T93: 4 | U93: 4 | V93: 4 | W93: 3 | X93: 4 | Y93: 5 | Z93: 5 | AA93: 5 | AB93: 5 | AC93: 5 | AD93: 5 | AE93: 3 | AF93: 4 | AG93: 4 | AH93: 1 | AI93: 2 | AJ93: 2 | AK93: 1 | AL93: Tools, stable internet connection | AM93: limited digital skills
... A95: =A94+1 -> 94 | B95: Treasurer | C95: 31-40 | D95: Female | E95: High School Level | F95: 3-5 yrs | G95: Kapit Bisig Tungo sa Pag-unlad ng Mamamayan Farmers and Fisherfolks Association | H95: 3-5 yrs | I95: 21-30 members | J95: 1-2 ha | K95: Fresh vegetables, Poultry | L95: No | M95: Public market, Direct selling, Online | N95: Above 20,000 | O95: Yes | P95: Mobile data | Q95: No | S95: 4 | T95: 3 | U95: 3 | V95: 3 | W95: 3 | X95: 3 | Y95: 5 | Z95: 4 | AA95: 3 | AB95: 4 | AC95: 4 | AD95: 4 | AE95: 4 | AF95: 4 | AG95: 4 | AH95: 3 | AI95: 3 | AJ95: 2 | AK95: 3 | AL95: Training, tools/devices | AM95: limited skills
A96: =A95+1 -> 95 | B96: President | C96: 18-30 | D96: Male | E96: College Grad | F96: 3-5 yrs | G96: Casapa Livestock Raisers Association (CLiRA) | H96: 3-5 yrs | I96: 21-30 members | J96: less than 1 ha | K96: Poultry | L96: No | M96: Trader, Direct selling, Online | N96: Above 20,000 | O96: Yes | P96: Mobile data | Q96: Yes | R96: Posting products on social media | S96: 3 | T96: 3 | U96: 3 | V96: 2 | W96: 2 | X96: 3 | Y96: 2 | Z96: 2 | AA96: 3 | AB96: 2 | AC96: 2 | AD96: 2 | AE96: 1 | AF96: 2 | AG96: 2 | AH96: 4 | AI96: 4 | AJ96: 4 | AK96: 4 | AL96: proper tools/ equipment to improve content creation | AM96: Limited tools /resources
A97: =A96+1 -> 96 | B97: Member | C97: 18-30 | D97: Male | E97: College Grad | F97: 3-5 yrs | G97: Casapa Livestock Raisers Association (CLiRA) | H97: 3-5 yrs | I97: 21-30 members | J97: less than 1 ha | K97: Poultry | L97: No | M97: Trader, Direct selling, Online | N97: Above 20,000 | O97: Yes | P97: WiFi | Q97: Yes | R97: Posting products on social media | S97: 4 | T97: 3 | U97: 3 | V97: 3 | W97: 2 | X97: 3 | Y97: 2 | Z97: 2 | AA97: 3 | AB97: 2 | AC97: 2 | AD97: 2 | AE97: 2 | AF97: 2 | AG97: 2 | AH97: 4 | AI97: 4 | AJ97: 4 | AK97: 4 | AL97: Additonal training, stable internet connection, tools/ equipment | AM97: limited content creation skills, unstable internet connection
A98: =A97+1 -> 97 | B98: President | C98: 41-50 | D98: Female | E98: High School Level | F98: 1-2 yrs | G98: Kauswagan Crop Farmers Association | H98: 1-2 yrs | I98: 11-20 members | J98: 1-2 ha | K98: Fresh vegetables | L98: No | M98: Trader, Direct selling | N98: Below 5,000 | O98: Yes | P98: Mobile data | Q98: No | S98: 4 | T98: 3 | U98: 3 | V98: 3 | W98: 3 | X98: 5 | Y98: 3 | Z98: 5 | AA98: 4 | AB98: 3 | AC98: 5 | AD98: 4 | AE98: 4 | AF98: 3 | AG98: 4 | AH98: 2 | AI98: 3 | AJ98: 2 | AK98: 2 | AL98: stable internet connection, tools | AM98: limited skills/ experience
A99: =A98+1 -> 98 | B99: Member | C99: 31-40 | D99: Female | E99: High School Level | F99: 1-2 yrs | G99: Kauswagan Crop Farmers Association | H99: 1-2 yrs | I99: 11-20 members | J99: 1-2 ha | K99: Fresh vegetables | L99: No | M99: Trader, Direct selling | N99: Below 5,000 | O99: Yes | P99: Mobile data | Q99: No | S99: 4 | T99: 3 | U99: 3 | V99: 4 | W99: 4 | X99: 4 | Y99: 4 | Z99: 4 | AA99: 3 | AB99: 3 | AC99: 5 | AD99: 3 | AE99: 3 | AF99: 3 | AG99: 3 | AH99: 1 | AI99: 2 | AJ99: 1 | AK99: 1 | AL99: stable internet connection, tools | AM99: limited skills/ experience
A100: =A99+1 -> 99 | B100: President | C100: 51 & above | D100: Male | E100: Elementray Graduate | F100: 1-2 yrs | G100: Calanyugan Farmers Association | H100: 1-2 yrs | I100: 11-20 members | J100: 1-2 ha | K100: Fresh vegetables, Poultry | L100: No | M100: Trader, Direct selling | N100: Above 20,000 | O100: Yes | P100: WiFi | Q100: No | S100: 5 | T100: 4 | U100: 4 | V100: 3 | W100: 3 | X100: 4 | Y100: 4 | Z100: 3 | AA100: 4 | AB100: 4 | AC100: 3 | AD100: 3 | AE100: 3 | AF100: 3 | AG100: 3 | AH100: 2 | AI100: 4 | AJ100: 2 | AK100: 2 | AL100: training | AM100: transportation for product delivery
A101: =A100+1 -> 100 | B101: Secretary | C101: 41-50 | D101: Female | E101: High School Graduate | F101: 1-2 yrs | G101: Calanyugan Farmers Association | H101: 1-2 yrs | I101: 11-20 members | J101: 1-2 ha | K101: Fresh vegetables, Poultry | L101: No | M101: Trader, Direct selling | N101: Above 20,000 | O101: Yes | P101: Mobile data | Q101: No | S101: 3 | T101: 3 | U101: 3 | V101: 3 | W101: 3 | X101: 4 | Y101: 4 | Z101: 4 | AA101: 4 | AB101: 3 | AC101: 3 | AD101: 3 | AE101: 4 | AF101: 4 | AG101: 4 | AH101: 2 | AI101: 4 | AJ101: 3 | AK101: 2 | AL101: training | AM101: transportation for product delivery
A102: =A101+1 -> 101 | B102: Secretary | C102: 41-50 | D102: Female | E102: High School Graduate | F102: 1-2 yrs | G102: Brgy. Lunang II Farmers and Fisherfolks Association | H102: 1-2 yrs | I102: 21-30 members | J102: less than 1 ha | K102: Fresh vegetables, Poultry | L102: No | M102: Trader, Direct selling, Online | N102: Above 20,000 | O102: Yes | P102: Both Mobile & WiFi | Q102: No | S102: 5 | T102: 5 | U102: 5 | V102: 4 | W102: 3 | X102: 4 | Y102: 4 | Z102: 4 | AA102: 4 | AB102: 4 | AC102: 3 | AD102: 3 | AE102: 4 | AF102: 3 | AG102: 4 | AH102: 3 | AI102: 2 | AJ102: 2 | AK102: 2 | AL102: training, stable internet connection | AM102: lack of strategy
A103: =A102+1 -> 102 | B103: Treasurer | C103: 41-50 | D103: Female | E103: High School Graduate | F103: 1-2 yrs | G103: Brgy. Lunang II Farmers and Fisherfolks Association | H103: 1-2 yrs | I103: 21-30 members | J103: less than 1 ha | K103: Fresh vegetables, Poultry | L103: No | M103: Trader, Direct selling, Online | N103: Above 20,000 | O103: Yes | P103: Both Mobile & WiFi | Q103: No | S103: 4 | T103: 4 | U103: 4 | V103: 3 | W103: 3 | X103: 4 | Y103: 4 | Z103: 4 | AA103: 4 | AB103: 3 | AC103: 3 | AD103: 3 | AE103: 5 | AF103: 3 | AG103: 3 | AH103: 3 | AI103: 3 | AJ103: 3 | AK103: 3 | AL103: training, stable internet connection | AM103: lack of strategy
A104: =A103+1 -> 103 | B104: President | C104: 51 & above | D104: Male | E104: High School Graduate | F104: 3-5 yrs | G104: Barangay Pinalangga Fishermens and Farmers Association | H104: 3-5 yrs | I104: 21-30 members | J104: less than 1 ha | K104: Livestock; Processed products | L104: Yes; tocino | M104: Trader, Direct selling, Online | N104: Above 20,000 | O104: Yes | P104: Both Mobile & WiFi | Q104: No | S104: 3 | T104: 3 | U104: 3 | V104: 3 | W104: 3 | X104: 3 | Y104: 4 | Z104: 4 | AA104: 4 | AB104: 3 | AC104: 3 | AD104: 3 | AE104: 5 | AF104: 3 | AG104: 3 | AH104: 3 | AI104: 4 | AJ104: 3 | AK104: 3 | AL104: training | AM104: transportation for product delivery
A105: =A104+1 -> 104 | B105: Secretary | C105: 41-50 | D105: Female | E105: High School | F105: 3-5 yrs | G105: Barangay Pinalangga Fishermens and Farmers Association | H105: 3-5 yrs | I105: 21-30 members | J105: less than 1 ha | K105: Livestock; Processed products | L105: Yes; tocino | M105: Trader, Direct selling, Online | N105: Above 20,000 | O105: Yes | P105: Both Mobile & WiFi | Q105: No | S105: 4 | T105: 3 | U105: 3 | V105: 3 | W105: 3 | X105: 5 | Y105: 3 | Z105: 5 | AA105: 4 | AB105: 3 | AC105: 5 | AD105: 4 | AE105: 4 | AF105: 3 | AG105: 4 | AH105: 2 | AI105: 3 | AJ105: 2 | AK105: 2 | AL105: training | AM105: transportation for product delivery
A106: =A105+1 -> 105 | B106: President | C106: 31-40 | D106: Female | E106: College Graduate | F106: 1-2 yrs | G106: Balocawe Hog Raisers Association | H106: 1-2 yrs | I106: 11-20 members | J106: less than 1 ha | K106: Livestock | L106: No | M106: Trader, Direct selling | N106: Above 20,000 | O106: Yes | P106: Both Mobile & WiFi | Q106: No | S106: 4 | T106: 3 | U106: 3 | V106: 4 | W106: 4 | X106: 4 | Y106: 4 | Z106: 4 | AA106: 3 | AB106: 3 | AC106: 5 | AD106: 3 | AE106: 3 | AF106: 3 | AG106: 3 | AH106: 1 | AI106: 2 | AJ106: 1 | AK106: 1 | AL106: stable internet connection, tools | AM106: limited skills/ experience
A107: =A106+1 -> 106 | B107: Secretary | C107: 31-40 | D107: Female | E107: High School Graduate | F107: 1-2 yrs | G107: Balocawe Hog Raisers Association | H107: 1-2 yrs | I107: 11-20 members | J107: less than 1 ha | K107: Livestock | L107: No | M107: Trader, Direct selling | N107: Above 20,000 | O107: Yes | P107: Both Mobile & WiFi | Q107: No | S107: 5 | T107: 4 | U107: 4 | V107: 3 | W107: 3 | X107: 4 | Y107: 4 | Z107: 3 | AA107: 4 | AB107: 4 | AC107: 3 | AD107: 3 | AE107: 3 | AF107: 3 | AG107: 3 | AH107: 2 | AI107: 4 | AJ107: 2 | AK107: 2 | AL107: stable internet connection, tools | AM107: limited skills/ experience
A108: =A107+1 -> 107 | B108: President | C108: 31-40 | D108: Male | E108: College Graduate | F108: 1-2 yrs | G108: Balogo Integrated Farmers Association | H108: 1-2 yrs | I108: 11-20 members | J108: less than 1 ha | K108: Poultry | L108: No | M108: Direct selling, Trader, Online | N108: Above 20,000 | O108: Yes | P108: WiFi | Q108: No | S108: 4 | T108: 3 | U108: 4 | V108: 3 | W108: 3 | X108: 3 | Y108: 4 | Z108: 4 | AA108: 4 | AB108: 3 | AC108: 4 | AD108: 3 | AE108: 4 | AF108: 4 | AG108: 4 | AH108: 3 | AI108: 2 | AJ108: 2 | AK108: 2 | AL108: stable internet connection, tools | AM108: not consistently using digital marketing
A109: =A108+1 -> 108 | B109: Treasurer | C109: 31-40 | D109: Female | E109: High School Grad | F109: 1-2 yrs | G109: Balogo Integrated Farmers Association | H109: 1-2 yrs | I109: 11-20 members | J109: less than 1 ha | K109: Poultry | L109: No | M109: Direct selling, Trader, Online | N109: Above 20,000 | O109: Yes | P109: WiFi | Q109: No | S109: 4 | T109: 4 | U109: 4 | V109: 4 | W109: 4 | X109: 4 | Y109: 4 | Z109: 4 | AA109: 4 | AB109: 3 | AC109: 4 | AD109: 4 | AE109: 4 | AF109: 4 | AG109: 4 | AH109: 3 | AI109: 3 | AJ109: 2 | AK109: 2 | AL109: stable internet connection, tools | AM109: limited skills/ experience

Sheet Aggregated
A1: Respondent No. | B1: Role | C1: Age_Range | D1: Sex | E1: Education | F1: Years_Managing | G1: Organization_Name | H1: Years_Established | I1: Membership _Size | J1: Farm_Size | K1: Commodity | L1: Value_Adding/ Processed_ Products_Specify | M1: Market | N1: Income_Level | O1: Has_Device | P1: Internet_ Type | Q1: Attended_Training | R1: Training_Details | S1: TB1 | T1: TB2 | U1: TB3 | V1: TB4 | W1: TB5 | X1: TB6 | Y1: OB7 | Z1: OB8 | AA1: OB9 | AB1: OB10 | AC1: OB11 | AD1: OB12 | AE1: EB13 | AF1: EB14 | AG1: EB15 | AH1: DMA16 | AI1: DMA17 | AJ1: DMA18 | AK1: DMA19 | AL1: Support_ Suggestions | AM1: Challenges
A2: 1 | G2: Sampao Small Water Irrigation System Association, Inc. | S2: =AVERAGE('Raw Data'!S2:S3) -> 4.5 | T2: =AVERAGE('Raw Data'!T2:T3) -> 5 | U2: =AVERAGE('Raw Data'!U2:U3) -> 4 | V2: =AVERAGE('Raw Data'!V2:V3) -> 4 | W2: =AVERAGE('Raw Data'!W2:W3) -> 4 | X2: =AVERAGE('Raw Data'!X2:X3) -> 4 | Y2: =AVERAGE('Raw Data'!Y2:Y3) -> 4.5 | Z2: =AVERAGE('Raw Data'!Z2:Z3) -> 4.5 | ... AK2: =AVERAGE('Raw Data'!AK2:AK3) -> 2.5
A3: =A2+1 -> 2 | G3: Pinangomhan Farmers Association | S3: =AVERAGE('Raw Data'!S4:S5) -> 5 | T3: =AVERAGE('Raw Data'!T4:T5) -> 4.5 | U3: =AVERAGE('Raw Data'!U4:U5) -> 5 | V3: =AVERAGE('Raw Data'!V4:V5) -> 3.5 | W3: =AVERAGE('Raw Data'!W4:W5) -> 3 | X3: =AVERAGE('Raw Data'!X4:X5) -> 4.5 | Y3: =AVERAGE('Raw Data'!Y4:Y5) -> 4 | Z3: =AVERAGE('Raw Data'!Z4:Z5) -> 4.5 | ... AK3: =AVERAGE('Raw Data'!AK4:AK5) -> 2.5
A4: =A3+1 -> 3 | G4: Culaba Integrated Hilltop Farm | S4: =AVERAGE('Raw Data'!S6:S7) -> 3.5 | T4: =AVERAGE('Raw Data'!T6:T7) -> 3.5 | U4: =AVERAGE('Raw Data'!U6:U7) -> 3.5 | V4: =AVERAGE('Raw Data'!V6:V7) -> 3 | W4: =AVERAGE('Raw Data'!W6:W7) -> 3 | X4: =AVERAGE('Raw Data'!X6:X7) -> 3.5 | Y4: =AVERAGE('Raw Data'!Y6:Y7) -> 4 | Z4: =AVERAGE('Raw Data'!Z6:Z7) -> 4 | ... AK4: =AVERAGE('Raw Data'!AK6:AK7) -> 3
A5: =A4+1 -> 4 | G5: Cabucgayan Farmers Association (CAFA) | S5: =AVERAGE('Raw Data'!S8:S9) -> 5 | T5: =AVERAGE('Raw Data'!T8:T9) -> 4.5 | U5: =AVERAGE('Raw Data'!U8:U9) -> 5 | V5: =AVERAGE('Raw Data'!V8:V9) -> 3.5 | W5: =AVERAGE('Raw Data'!W8:W9) -> 4.5 | X5: =AVERAGE('Raw Data'!X8:X9) -> 5 | Y5: =AVERAGE('Raw Data'!Y8:Y9) -> 5 | Z5: =AVERAGE('Raw Data'!Z8:Z9) -> 5 | ... AK5: =AVERAGE('Raw Data'!AK8:AK9) -> 1
A6: =A5+1 -> 5 | G6: Samahan ng mga Manggagawa Para sa Agrikulturang Pangkabuhayan (SMAP) | S6: =AVERAGE('Raw Data'!S10:S11) -> 4.5 | T6: =AVERAGE('Raw Data'!T10:T11) -> 4 | U6: =AVERAGE('Raw Data'!U10:U11) -> 4 | V6: =AVERAGE('Raw Data'!V10:V11) -> 4 | W6: =AVERAGE('Raw Data'!W10:W11) -> 4 | X6: =AVERAGE('Raw Data'!X10:X11) -> 4 | Y6: =AVERAGE('Raw Data'!Y10:Y11) -> 4.5 | Z6: =AVERAGE('Raw Data'!Z10:Z11) -> 4.5 | ... AK6: =AVERAGE('Raw Data'!AK10:AK11) -> 1.5
A7: =A6+1 -> 6 | G7: Tucdao-Anas Farmers’ Irrigator’s Association, Inc. | S7: =AVERAGE('Raw Data'!S12:S13) -> 5 | T7: =AVERAGE('Raw Data'!T12:T13) -> 4.5 | U7: =AVERAGE('Raw Data'!U12:U13) -> 4.5 | V7: =AVERAGE('Raw Data'!V12:V13) -> 3.5 | W7: =AVERAGE('Raw Data'!W12:W13) -> 4 | X7: =AVERAGE('Raw Data'!X12:X13) -> 4 | Y7: =AVERAGE('Raw Data'!Y12:Y13) -> 3.5 | Z7: =AVERAGE('Raw Data'!Z12:Z13) -> 4.5 | ... AK7: =AVERAGE('Raw Data'!AK12:AK13) -> 2
A8: =A7+1 -> 7 | G8: Maripipi Farmers and Fisherfolks Association | S8: =AVERAGE('Raw Data'!S14:S15) -> 4.5 | T8: =AVERAGE('Raw Data'!T14:T15) -> 4 | U8: =AVERAGE('Raw Data'!U14:U15) -> 4 | V8: =AVERAGE('Raw Data'!V14:V15) -> 3 | W8: =AVERAGE('Raw Data'!W14:W15) -> 3.5 | X8: =AVERAGE('Raw Data'!X14:X15) -> 4.5 | Y8: =AVERAGE('Raw Data'!Y14:Y15) -> 4 | Z8: =AVERAGE('Raw Data'!Z14:Z15) -> 5 | ... AK8: =AVERAGE('Raw Data'!AK14:AK15) -> 2.5
A9: =A8+1 -> 8 | G9: Bariis Corn Farmers Association | S9: =AVERAGE('Raw Data'!S16:S17) -> 5 | T9: =AVERAGE('Raw Data'!T16:T17) -> 4 | U9: =AVERAGE('Raw Data'!U16:U17) -> 4.5 | V9: =AVERAGE('Raw Data'!V16:V17) -> 3.5 | W9: =AVERAGE('Raw Data'!W16:W17) -> 3.5 | X9: =AVERAGE('Raw Data'!X16:X17) -> 3.5 | Y9: =AVERAGE('Raw Data'!Y16:Y17) -> 4 | Z9: =AVERAGE('Raw Data'!Z16:Z17) -> 4.5 | ... AK9: =AVERAGE('Raw Data'!AK16:AK17) -> 3
A10: =A9+1 -> 9 | G10: Mga Aktibong Ina sa Brgy. Pinamihagan | S10: =AVERAGE('Raw Data'!S18:S19) -> 5 | T10: =AVERAGE('Raw Data'!T18:T19) -> 5 | U10: =AVERAGE('Raw Data'!U18:U19) -> 5 | V10: =AVERAGE('Raw Data'!V18:V19) -> 4 | W10: =AVERAGE('Raw Data'!W18:W19) -> 4.5 | X10: =AVERAGE('Raw Data'!X18:X19) -> 4 | Y10: =AVERAGE('Raw Data'!Y18:Y19) -> 4.5 | Z10: =AVERAGE('Raw Data'!Z18:Z19) -> 4.5 | ... AK10: =AVERAGE('Raw Data'!AK18:AK19) -> 1
A11: =A10+1 -> 10 | G11: Tamarindo Integrated Peace Development Workers Association (TIPDWA) | S11: =AVERAGE('Raw Data'!S20:S21) -> 4 | T11: =AVERAGE('Raw Data'!T20:T21) -> 3.5 | U11: =AVERAGE('Raw Data'!U20:U21) -> 4 | V11: =AVERAGE('Raw Data'!V20:V21) -> 3.5 | W11: =AVERAGE('Raw Data'!W20:W21) -> 3.5 | X11: =AVERAGE('Raw Data'!X20:X21) -> 3.5 | Y11: =AVERAGE('Raw Data'!Y20:Y21) -> 4 | Z11: =AVERAGE('Raw Data'!Z20:Z21) -> 3.5 | ... AK11: =AVERAGE('Raw Data'!AK20:AK21) -> 1.5
A12: =A11+1 -> 11 | G12: Barangay Aringit Farmers Association | S12: =AVERAGE('Raw Data'!S22:S23) -> 5 | T12: =AVERAGE('Raw Data'!T22:T23) -> 4 | U12: =AVERAGE('Raw Data'!U22:U23) -> 3 | V12: =AVERAGE('Raw Data'!V22:V23) -> 3.5 | W12: =AVERAGE('Raw Data'!W22:W23) -> 3.5 | X12: =AVERAGE('Raw Data'!X22:X23) -> 4 | Y12: =AVERAGE('Raw Data'!Y22:Y23) -> 4.5 | Z12: =AVERAGE('Raw Data'!Z22:Z23) -> 4.5 | ... AK12: =AVERAGE('Raw Data'!AK22:AK23) -> 3
A13: =A12+1 -> 12 | G13: Julitanhon Integrated Farmers Association | S13: =AVERAGE('Raw Data'!S24:S25) -> 3 | T13: =AVERAGE('Raw Data'!T24:T25) -> 4 | U13: =AVERAGE('Raw Data'!U24:U25) -> 3.5 | V13: =AVERAGE('Raw Data'!V24:V25) -> 3 | W13: =AVERAGE('Raw Data'!W24:W25) -> 3.5 | X13: =AVERAGE('Raw Data'!X24:X25) -> 4.5 | Y13: =AVERAGE('Raw Data'!Y24:Y25) -> 4 | Z13: =AVERAGE('Raw Data'!Z24:Z25) -> 4.5 | ... AK13: =AVERAGE('Raw Data'!AK24:AK25) -> 2
A14: =A13+1 -> 13 | G14: Pagburublig han Parag-uma Association | S14: =AVERAGE('Raw Data'!S26:S27) -> 4 | T14: =AVERAGE('Raw Data'!T26:T27) -> 3 | U14: =AVERAGE('Raw Data'!U26:U27) -> 3.5 | V14: =AVERAGE('Raw Data'!V26:V27) -> 3 | W14: =AVERAGE('Raw Data'!W26:W27) -> 3.5 | X14: =AVERAGE('Raw Data'!X26:X27) -> 4 | Y14: =AVERAGE('Raw Data'!Y26:Y27) -> 3 | Z14: =AVERAGE('Raw Data'!Z26:Z27) -> 4 | ... AK14: =AVERAGE('Raw Data'!AK26:AK27) -> 3
A15: =A14+1 -> 14 | G15: Guingauan Small Farmers Association | S15: =AVERAGE('Raw Data'!S28:S29) -> 4.5 | T15: =AVERAGE('Raw Data'!T28:T29) -> 3.5 | U15: =AVERAGE('Raw Data'!U28:U29) -> 4 | V15: =AVERAGE('Raw Data'!V28:V29) -> 3 | W15: =AVERAGE('Raw Data'!W28:W29) -> 3.5 | X15: =AVERAGE('Raw Data'!X28:X29) -> 4 | Y15: =AVERAGE('Raw Data'!Y28:Y29) -> 4.5 | Z15: =AVERAGE('Raw Data'!Z28:Z29) -> 4.5 | ... AK15: =AVERAGE('Raw Data'!AK28:AK29) -> 1.5
A16: =A15+1 -> 15 | G16: Assuncion Del Senior Integrated Farmers Association | S16: =AVERAGE('Raw Data'!S30:S31) -> 5 | T16: =AVERAGE('Raw Data'!T30:T31) -> 5 | U16: =AVERAGE('Raw Data'!U30:U31) -> 5 | V16: =AVERAGE('Raw Data'!V30:V31) -> 4.5 | W16: =AVERAGE('Raw Data'!W30:W31) -> 4.5 | X16: =AVERAGE('Raw Data'!X30:X31) -> 4.5 | Y16: =AVERAGE('Raw Data'!Y30:Y31) -> 5 | Z16: =AVERAGE('Raw Data'!Z30:Z31) -> 5 | ... AK16: =AVERAGE('Raw Data'!AK30:AK31) -> 1.5
A17: =A16+1 -> 16 | G17: San Vicente Farmers and Fisherfolks Association | S17: =AVERAGE('Raw Data'!S32:S33) -> 3.5 | T17: =AVERAGE('Raw Data'!T32:T33) -> 3.5 | U17: =AVERAGE('Raw Data'!U32:U33) -> 3.5 | V17: =AVERAGE('Raw Data'!V32:V33) -> 3 | W17: =AVERAGE('Raw Data'!W32:W33) -> 3 | X17: =AVERAGE('Raw Data'!X32:X33) -> 4 | Y17: =AVERAGE('Raw Data'!Y32:Y33) -> 4.5 | Z17: =AVERAGE('Raw Data'!Z32:Z33) -> 4.5 | ... AK17: =AVERAGE('Raw Data'!AK32:AK33) -> 2.5
A18: =A17+1 -> 17 | G18: Blissful N' Abound Integrated Farmers Association | S18: =AVERAGE('Raw Data'!S34:S35) -> 3.5 | T18: =AVERAGE('Raw Data'!T34:T35) -> 3.5 | U18: =AVERAGE('Raw Data'!U34:U35) -> 3.5 | V18: =AVERAGE('Raw Data'!V34:V35) -> 4.5 | W18: =AVERAGE('Raw Data'!W34:W35) -> 4.5 | X18: =AVERAGE('Raw Data'!X34:X35) -> 4 | Y18: =AVERAGE('Raw Data'!Y34:Y35) -> 5 | Z18: =AVERAGE('Raw Data'!Z34:Z35) -> 5 | ... AK18: =AVERAGE('Raw Data'!AK34:AK35) -> 2
A19: =A18+1 -> 18 | G19: District 4 Rice, Coconut and Banana Farmers Association | S19: =AVERAGE('Raw Data'!S36:S37) -> 4 | T19: =AVERAGE('Raw Data'!T36:T37) -> 4.5 | U19: =AVERAGE('Raw Data'!U36:U37) -> 4.5 | V19: =AVERAGE('Raw Data'!V36:V37) -> 3.5 | W19: =AVERAGE('Raw Data'!W36:W37) -> 4 | X19: =AVERAGE('Raw Data'!X36:X37) -> 4.5 | Y19: =AVERAGE('Raw Data'!Y36:Y37) -> 4 | Z19: =AVERAGE('Raw Data'!Z36:Z37) -> 4 | ... AK19: =AVERAGE('Raw Data'!AK36:AK37) -> 1
A20: =A19+1 -> 19 | G20: Lamaca Farmers Association | S20: =AVERAGE('Raw Data'!S38:S39) -> 4 | T20: =AVERAGE('Raw Data'!T38:T39) -> 3.5 | U20: =AVERAGE('Raw Data'!U38:U39) -> 3.5 | V20: =AVERAGE('Raw Data'!V38:V39) -> 3 | W20: =AVERAGE('Raw Data'!W38:W39) -> 3 | X20: =AVERAGE('Raw Data'!X38:X39) -> 3 | Y20: =AVERAGE('Raw Data'!Y38:Y39) -> 3.5 | Z20: =AVERAGE('Raw Data'!Z38:Z39) -> 4 | ... AK20: =AVERAGE('Raw Data'!AK38:AK39) -> 2
A21: =A20+1 -> 20 | G21: San Roque Farmers and Fisherfolks Association | S21: =AVERAGE('Raw Data'!S40:S41) -> 4 | T21: =AVERAGE('Raw Data'!T40:T41) -> 3 | U21: =AVERAGE('Raw Data'!U40:U41) -> 3 | V21: =AVERAGE('Raw Data'!V40:V41) -> 3.5 | W21: =AVERAGE('Raw Data'!W40:W41) -> 3.5 | X21: =AVERAGE('Raw Data'!X40:X41) -> 4.5 | Y21: =AVERAGE('Raw Data'!Y40:Y41) -> 3.5 | Z21: =AVERAGE('Raw Data'!Z40:Z41) -> 4.5 | ... AK21: =AVERAGE('Raw Data'!AK40:AK41) -> 1.5
A22: =A21+1 -> 21 | G22: Calintaan Farmers Association | S22: =AVERAGE('Raw Data'!S42:S43) -> 5 | T22: =AVERAGE('Raw Data'!T42:T43) -> 4 | U22: =AVERAGE('Raw Data'!U42:U43) -> 4 | V22: =AVERAGE('Raw Data'!V42:V43) -> 3 | W22: =AVERAGE('Raw Data'!W42:W43) -> 3.5 | X22: =AVERAGE('Raw Data'!X42:X43) -> 4 | Y22: =AVERAGE('Raw Data'!Y42:Y43) -> 4 | Z22: =AVERAGE('Raw Data'!Z42:Z43) -> 3.5 | ... AK22: =AVERAGE('Raw Data'!AK42:AK43) -> 2.5
A23: =A22+1 -> 22 | G23: Barangay Dayanog Small Coconut Farmers and Fisherfolks Association | S23: =AVERAGE('Raw Data'!S44:S45) -> 5 | T23: =AVERAGE('Raw Data'!T44:T45) -> 5 | U23: =AVERAGE('Raw Data'!U44:U45) -> 4 | V23: =AVERAGE('Raw Data'!V44:V45) -> 4 | W23: =AVERAGE('Raw Data'!W44:W45) -> 4 | X23: =AVERAGE('Raw Data'!X44:X45) -> 4.5 | Y23: =AVERAGE('Raw Data'!Y44:Y45) -> 5 | Z23: =AVERAGE('Raw Data'!Z44:Z45) -> 5 | ... AK23: =AVERAGE('Raw Data'!AK44:AK45) -> 1
A24: =A23+1 -> 23 | G24: PUNDOK MAAMUMAHON | S24: =AVERAGE('Raw Data'!S46:S47) -> 3.5 | T24: =AVERAGE('Raw Data'!T46:T47) -> 3 | U24: =AVERAGE('Raw Data'!U46:U47) -> 3 | V24: =AVERAGE('Raw Data'!V46:V47) -> 3 | W24: =AVERAGE('Raw Data'!W46:W47) -> 3 | X24: =AVERAGE('Raw Data'!X46:X47) -> 4 | Y24: =AVERAGE('Raw Data'!Y46:Y47) -> 4 | Z24: =AVERAGE('Raw Data'!Z46:Z47) -> 4 | ... AK24: =AVERAGE('Raw Data'!AK46:AK47) -> 1.5
A25: =A24+1 -> 24 | G25: Coot-Dinahugan Integrated Farming Association | S25: =AVERAGE('Raw Data'!S48:S49) -> 5 | T25: =AVERAGE('Raw Data'!T48:T49) -> 4.5 | U25: =AVERAGE('Raw Data'!U48:U49) -> 4.5 | V25: =AVERAGE('Raw Data'!V48:V49) -> 4 | W25: =AVERAGE('Raw Data'!W48:W49) -> 4 | X25: =AVERAGE('Raw Data'!X48:X49) -> 5 | Y25: =AVERAGE('Raw Data'!Y48:Y49) -> 4 | Z25: =AVERAGE('Raw Data'!Z48:Z49) -> 5 | ... AK25: =AVERAGE('Raw Data'!AK48:AK49) -> 1
A26: =A25+1 -> 25 | G26: Magallanes Farmers Association | S26: =AVERAGE('Raw Data'!S50:S51) -> 4.5 | T26: =AVERAGE('Raw Data'!T50:T51) -> 4 | U26: =AVERAGE('Raw Data'!U50:U51) -> 3.5 | V26: =AVERAGE('Raw Data'!V50:V51) -> 3 | W26: =AVERAGE('Raw Data'!W50:W51) -> 3.5 | X26: =AVERAGE('Raw Data'!X50:X51) -> 3.5 | Y26: =AVERAGE('Raw Data'!Y50:Y51) -> 3.5 | Z26: =AVERAGE('Raw Data'!Z50:Z51) -> 3 | ... AK26: =AVERAGE('Raw Data'!AK50:AK51) -> 2.5
A27: =A26+1 -> 26 | G27: Pinamudlan Women's Association | S27: =AVERAGE('Raw Data'!S52:S53) -> 5 | T27: =AVERAGE('Raw Data'!T52:T53) -> 4 | U27: =AVERAGE('Raw Data'!U52:U53) -> 4.5 | V27: =AVERAGE('Raw Data'!V52:V53) -> 4 | W27: =AVERAGE('Raw Data'!W52:W53) -> 4 | X27: =AVERAGE('Raw Data'!X52:X53) -> 4 | Y27: =AVERAGE('Raw Data'!Y52:Y53) -> 4.5 | Z27: =AVERAGE('Raw Data'!Z52:Z53) -> 4.5 | ... AK27: =AVERAGE('Raw Data'!AK52:AK53) -> 2
A28: =A27+1 -> 27 | G28: Maalagaron Abtik Responsable Ug Ehemplo Nga Mga Kababayen-An (MARE) CARES sa Hinapo Women’s Association | S28: =AVERAGE('Raw Data'!S54:S55) -> 4.5 | T28: =AVERAGE('Raw Data'!T54:T55) -> 4 | U28: =AVERAGE('Raw Data'!U54:U55) -> 4 | V28: =AVERAGE('Raw Data'!V54:V55) -> 4 | W28: =AVERAGE('Raw Data'!W54:W55) -> 4 | X28: =AVERAGE('Raw Data'!X54:X55) -> 4.5 | Y28: =AVERAGE('Raw Data'!Y54:Y55) -> 4.5 | Z28: =AVERAGE('Raw Data'!Z54:Z55) -> 5 | ... AK28: =AVERAGE('Raw Data'!AK54:AK55) -> 1.5
A29: =A28+1 -> 28 | G29: Cabulisan Farmers Association | S29: =AVERAGE('Raw Data'!S56:S57) -> 4 | T29: =AVERAGE('Raw Data'!T56:T57) -> 3.5 | U29: =AVERAGE('Raw Data'!U56:U57) -> 3.5 | V29: =AVERAGE('Raw Data'!V56:V57) -> 4 | W29: =AVERAGE('Raw Data'!W56:W57) -> 4.5 | X29: =AVERAGE('Raw Data'!X56:X57) -> 4.5 | Y29: =AVERAGE('Raw Data'!Y56:Y57) -> 4 | Z29: =AVERAGE('Raw Data'!Z56:Z57) -> 5 | ... AK29: =AVERAGE('Raw Data'!AK56:AK57) -> 1.5
A30: =A29+1 -> 29 | G30: Talisay Women's Association | S30: =AVERAGE('Raw Data'!S58:S59) -> 5 | T30: =AVERAGE('Raw Data'!T58:T59) -> 4.5 | U30: =AVERAGE('Raw Data'!U58:U59) -> 5 | V30: =AVERAGE('Raw Data'!V58:V59) -> 4 | W30: =AVERAGE('Raw Data'!W58:W59) -> 3.5 | X30: =AVERAGE('Raw Data'!X58:X59) -> 4.5 | Y30: =AVERAGE('Raw Data'!Y58:Y59) -> 4.5 | Z30: =AVERAGE('Raw Data'!Z58:Z59) -> 5 | ... AK30: =AVERAGE('Raw Data'!AK58:AK59) -> 1.5
A31: =A30+1 -> 30 | G31: Sabang II Rural Improvement Club | S31: =AVERAGE('Raw Data'!S60:S61) -> 3.5 | T31: =AVERAGE('Raw Data'!T60:T61) -> 3.5 | U31: =AVERAGE('Raw Data'!U60:U61) -> 3 | V31: =AVERAGE('Raw Data'!V60:V61) -> 3 | W31: =AVERAGE('Raw Data'!W60:W61) -> 3.5 | X31: =AVERAGE('Raw Data'!X60:X61) -> 4 | Y31: =AVERAGE('Raw Data'!Y60:Y61) -> 3.5 | Z31: =AVERAGE('Raw Data'!Z60:Z61) -> 4.5 | ... AK31: =AVERAGE('Raw Data'!AK60:AK61) -> 3
A32: =A31+1 -> 31 | G32: Aguada Fisherfolks Mangrove Kinis and Bangus Sustainable Association | S32: =AVERAGE('Raw Data'!S62:S63) -> 4.5 | T32: =AVERAGE('Raw Data'!T62:T63) -> 4.5 | U32: =AVERAGE('Raw Data'!U62:U63) -> 4 | V32: =AVERAGE('Raw Data'!V62:V63) -> 4 | W32: =AVERAGE('Raw Data'!W62:W63) -> 4 | X32: =AVERAGE('Raw Data'!X62:X63) -> 4.5 | Y32: =AVERAGE('Raw Data'!Y62:Y63) -> 4 | Z32: =AVERAGE('Raw Data'!Z62:Z63) -> 5 | ... AK32: =AVERAGE('Raw Data'!AK62:AK63) -> 2
A33: =A32+1 -> 32 | G33: Magsasakang Masisipag ng Mapanas (3M) Association | S33: =AVERAGE('Raw Data'!S64:S65) -> 4.5 | T33: =AVERAGE('Raw Data'!T64:T65) -> 4 | U33: =AVERAGE('Raw Data'!U64:U65) -> 4 | V33: =AVERAGE('Raw Data'!V64:V65) -> 3.5 | W33: =AVERAGE('Raw Data'!W64:W65) -> 3.5 | X33: =AVERAGE('Raw Data'!X64:X65) -> 4.5 | Y33: =AVERAGE('Raw Data'!Y64:Y65) -> 4.5 | Z33: =AVERAGE('Raw Data'!Z64:Z65) -> 5 | ... AK33: =AVERAGE('Raw Data'!AK64:AK65) -> 2.5
A34: =A33+1 -> 33 | G34: Pio Del Pilar Farmers Association | S34: =AVERAGE('Raw Data'!S66:S67) -> 4 | T34: =AVERAGE('Raw Data'!T66:T67) -> 4 | U34: =AVERAGE('Raw Data'!U66:U67) -> 4 | V34: =AVERAGE('Raw Data'!V66:V67) -> 3 | W34: =AVERAGE('Raw Data'!W66:W67) -> 3.5 | X34: =AVERAGE('Raw Data'!X66:X67) -> 3 | Y34: =AVERAGE('Raw Data'!Y66:Y67) -> 4 | Z34: =AVERAGE('Raw Data'!Z66:Z67) -> 3 | ... AK34: =AVERAGE('Raw Data'!AK66:AK67) -> 1.5
A35: =A34+1 -> 34 | G35: Victoria Vegetable Producers Association | S35: =AVERAGE('Raw Data'!S68:S69) -> 4 | T35: =AVERAGE('Raw Data'!T68:T69) -> 3.5 | U35: =AVERAGE('Raw Data'!U68:U69) -> 4 | V35: =AVERAGE('Raw Data'!V68:V69) -> 3.5 | W35: =AVERAGE('Raw Data'!W68:W69) -> 3 | X35: =AVERAGE('Raw Data'!X68:X69) -> 4 | Y35: =AVERAGE('Raw Data'!Y68:Y69) -> 3.5 | Z35: =AVERAGE('Raw Data'!Z68:Z69) -> 4 | ... AK35: =AVERAGE('Raw Data'!AK68:AK69) -> 2
A36: =A35+1 -> 35 | G36: Bagong Sabang Vegetable Raisers Association | S36: =AVERAGE('Raw Data'!S70:S71) -> 4.5 | T36: =AVERAGE('Raw Data'!T70:T71) -> 4 | U36: =AVERAGE('Raw Data'!U70:U71) -> 3.5 | V36: =AVERAGE('Raw Data'!V70:V71) -> 3.5 | W36: =AVERAGE('Raw Data'!W70:W71) -> 4 | X36: =AVERAGE('Raw Data'!X70:X71) -> 4.5 | Y36: =AVERAGE('Raw Data'!Y70:Y71) -> 4.5 | Z36: =AVERAGE('Raw Data'!Z70:Z71) -> 5 | ... AK36: =AVERAGE('Raw Data'!AK70:AK71) -> 1
A37: =A36+1 -> 36 | G37: Destacado Farmers Association | S37: =AVERAGE('Raw Data'!S72:S73) -> 4 | T37: =AVERAGE('Raw Data'!T72:T73) -> 3 | U37: =AVERAGE('Raw Data'!U72:U73) -> 3.5 | V37: =AVERAGE('Raw Data'!V72:V73) -> 3.5 | W37: =AVERAGE('Raw Data'!W72:W73) -> 3 | X37: =AVERAGE('Raw Data'!X72:X73) -> 3.5 | Y37: =AVERAGE('Raw Data'!Y72:Y73) -> 3.5 | Z37: =AVERAGE('Raw Data'!Z72:Z73) -> 4.5 | ... AK37: =AVERAGE('Raw Data'!AK72:AK73) -> 1.5
A38: =A37+1 -> 37 | G38: Cawayan Farmers and Fisherfolks Association | S38: =AVERAGE('Raw Data'!S74:S75) -> 3 | T38: =AVERAGE('Raw Data'!T74:T75) -> 4 | U38: =AVERAGE('Raw Data'!U74:U75) -> 3.5 | V38: =AVERAGE('Raw Data'!V74:V75) -> 3 | W38: =AVERAGE('Raw Data'!W74:W75) -> 3.5 | X38: =AVERAGE('Raw Data'!X74:X75) -> 3.5 | Y38: =AVERAGE('Raw Data'!Y74:Y75) -> 4.5 | Z38: =AVERAGE('Raw Data'!Z74:Z75) -> 4.5 | ... AK38: =AVERAGE('Raw Data'!AK74:AK75) -> 1
A39: =A38+1 -> 38 | G39: Capul Poblacion Integrated Farmers Association | S39: =AVERAGE('Raw Data'!S76:S77) -> 5 | T39: =AVERAGE('Raw Data'!T76:T77) -> 4.5 | U39: =AVERAGE('Raw Data'!U76:U77) -> 5 | V39: =AVERAGE('Raw Data'!V76:V77) -> 3.5 | W39: =AVERAGE('Raw Data'!W76:W77) -> 3 | X39: =AVERAGE('Raw Data'!X76:X77) -> 3.5 | Y39: =AVERAGE('Raw Data'!Y76:Y77) -> 4.5 | Z39: =AVERAGE('Raw Data'!Z76:Z77) -> 3.5 | ... AK39: =AVERAGE('Raw Data'!AK76:AK77) -> 2
A40: =A39+1 -> 39 | G40: Manraya Fisherfolks and Farmers Association | S40: =AVERAGE('Raw Data'!S78:S79) -> 4.5 | T40: =AVERAGE('Raw Data'!T78:T79) -> 4.5 | U40: =AVERAGE('Raw Data'!U78:U79) -> 4.5 | V40: =AVERAGE('Raw Data'!V78:V79) -> 3.5 | W40: =AVERAGE('Raw Data'!W78:W79) -> 3 | X40: =AVERAGE('Raw Data'!X78:X79) -> 4 | Y40: =AVERAGE('Raw Data'!Y78:Y79) -> 4 | Z40: =AVERAGE('Raw Data'!Z78:Z79) -> 4 | ... AK40: =AVERAGE('Raw Data'!AK78:AK79) -> 2.5
A41: =A40+1 -> 40 | G41: Bolusao Coconut Based Integrated FA | S41: =AVERAGE('Raw Data'!S80:S81) -> 3 | T41: =AVERAGE('Raw Data'!T80:T81) -> 3 | U41: =AVERAGE('Raw Data'!U80:U81) -> 3 | V41: =AVERAGE('Raw Data'!V80:V81) -> 3 | W41: =AVERAGE('Raw Data'!W80:W81) -> 3 | X41: =AVERAGE('Raw Data'!X80:X81) -> 3.5 | Y41: =AVERAGE('Raw Data'!Y80:Y81) -> 4 | Z41: =AVERAGE('Raw Data'!Z80:Z81) -> 4 | ... AK41: =AVERAGE('Raw Data'!AK80:AK81) -> 2.5
A42: =A41+1 -> 41 | G42: San Isidro Women's Association | S42: =AVERAGE('Raw Data'!S82:S83) -> 4 | T42: =AVERAGE('Raw Data'!T82:T83) -> 3 | U42: =AVERAGE('Raw Data'!U82:U83) -> 3.5 | V42: =AVERAGE('Raw Data'!V82:V83) -> 3 | W42: =AVERAGE('Raw Data'!W82:W83) -> 3 | X42: =AVERAGE('Raw Data'!X82:X83) -> 4 | Y42: =AVERAGE('Raw Data'!Y82:Y83) -> 4 | Z42: =AVERAGE('Raw Data'!Z82:Z83) -> 4 | ... AK42: =AVERAGE('Raw Data'!AK82:AK83) -> 3
A43: =A42+1 -> 42 | G43: Sagkaray Farmers and Development Association | S43: =AVERAGE('Raw Data'!S84:S85) -> 4 | T43: =AVERAGE('Raw Data'!T84:T85) -> 3.5 | U43: =AVERAGE('Raw Data'!U84:U85) -> 4 | V43: =AVERAGE('Raw Data'!V84:V85) -> 3 | W43: =AVERAGE('Raw Data'!W84:W85) -> 3 | X43: =AVERAGE('Raw Data'!X84:X85) -> 3.5 | Y43: =AVERAGE('Raw Data'!Y84:Y85) -> 4.5 | Z43: =AVERAGE('Raw Data'!Z84:Z85) -> 3.5 | ... AK43: =AVERAGE('Raw Data'!AK84:AK85) -> 2
A44: =A43+1 -> 43 | G44: Tanglad Farmers Association | S44: =AVERAGE('Raw Data'!S86:S87) -> 4.5 | T44: =AVERAGE('Raw Data'!T86:T87) -> 4.5 | U44: =AVERAGE('Raw Data'!U86:U87) -> 4.5 | V44: =AVERAGE('Raw Data'!V86:V87) -> 3.5 | W44: =AVERAGE('Raw Data'!W86:W87) -> 3 | X44: =AVERAGE('Raw Data'!X86:X87) -> 4 | Y44: =AVERAGE('Raw Data'!Y86:Y87) -> 4 | Z44: =AVERAGE('Raw Data'!Z86:Z87) -> 4 | ... AK44: =AVERAGE('Raw Data'!AK86:AK87) -> 2.5
A45: =A44+1 -> 44 | G45: Buyayawon Farmers Association | S45: =AVERAGE('Raw Data'!S88:S89) -> 3.5 | T45: =AVERAGE('Raw Data'!T88:T89) -> 3 | U45: =AVERAGE('Raw Data'!U88:U89) -> 3 | V45: =AVERAGE('Raw Data'!V88:V89) -> 3 | W45: =AVERAGE('Raw Data'!W88:W89) -> 3 | X45: =AVERAGE('Raw Data'!X88:X89) -> 4 | Y45: =AVERAGE('Raw Data'!Y88:Y89) -> 3.5 | Z45: =AVERAGE('Raw Data'!Z88:Z89) -> 4.5 | ... AK45: =AVERAGE('Raw Data'!AK88:AK89) -> 2.5
A46: =A45+1 -> 45 | G46: Bangon-Alugan-Tanauan-Sta. Cruz Corn and Cassava FA | S46: =AVERAGE('Raw Data'!S90:S91) -> 4.5 | T46: =AVERAGE('Raw Data'!T90:T91) -> 3.5 | U46: =AVERAGE('Raw Data'!U90:U91) -> 3.5 | V46: =AVERAGE('Raw Data'!V90:V91) -> 3.5 | W46: =AVERAGE('Raw Data'!W90:W91) -> 3.5 | X46: =AVERAGE('Raw Data'!X90:X91) -> 4 | Y46: =AVERAGE('Raw Data'!Y90:Y91) -> 4 | Z46: =AVERAGE('Raw Data'!Z90:Z91) -> 3.5 | ... AK46: =AVERAGE('Raw Data'!AK90:AK91) -> 1.5
A47: =A46+1 -> 46 | G47: Mabuhay Farmers Peace Builders and Development Association | S47: =AVERAGE('Raw Data'!S92:S93) -> 5 | T47: =AVERAGE('Raw Data'!T92:T93) -> 4 | U47: =AVERAGE('Raw Data'!U92:U93) -> 4 | V47: =AVERAGE('Raw Data'!V92:V93) -> 3.5 | W47: =AVERAGE('Raw Data'!W92:W93) -> 3 | X47: =AVERAGE('Raw Data'!X92:X93) -> 4 | Y47: =AVERAGE('Raw Data'!Y92:Y93) -> 5 | Z47: =AVERAGE('Raw Data'!Z92:Z93) -> 5 | ... AK47: =AVERAGE('Raw Data'!AK92:AK93) -> 1.5
A48: =A47+1 -> 47 | G48: Kapit Bisig Tungo sa Pag-unlad ng Mamamayan Farmers and Fisherfolks Association | S48: =AVERAGE('Raw Data'!S94:S95) -> 4 | T48: =AVERAGE('Raw Data'!T94:T95) -> 3.5 | U48: =AVERAGE('Raw Data'!U94:U95) -> 3.5 | V48: =AVERAGE('Raw Data'!V94:V95) -> 3.5 | W48: =AVERAGE('Raw Data'!W94:W95) -> 3.5 | X48: =AVERAGE('Raw Data'!X94:X95) -> 3.5 | Y48: =AVERAGE('Raw Data'!Y94:Y95) -> 4.5 | Z48: =AVERAGE('Raw Data'!Z94:Z95) -> 4.5 | ... AK48: =AVERAGE('Raw Data'!AK94:AK95) -> 2
A49: =A48+1 -> 48 | G49: Casapa Livestock Raisers Association (CLiRA) | S49: =AVERAGE('Raw Data'!S96:S97) -> 3.5 | T49: =AVERAGE('Raw Data'!T96:T97) -> 3 | U49: =AVERAGE('Raw Data'!U96:U97) -> 3 | V49: =AVERAGE('Raw Data'!V96:V97) -> 2.5 | W49: =AVERAGE('Raw Data'!W96:W97) -> 2 | X49: =AVERAGE('Raw Data'!X96:X97) -> 3 | Y49: =AVERAGE('Raw Data'!Y96:Y97) -> 2 | Z49: =AVERAGE('Raw Data'!Z96:Z97) -> 2 | ... AK49: =AVERAGE('Raw Data'!AK96:AK97) -> 4
A50: =A49+1 -> 49 | G50: Kauswagan Crop Farmers Association
A51: =A50+1 -> 50 | G51: Calanyugan Farmers Association | S51: =AVERAGE('Raw Data'!S100:S101) -> 4 | T51: =AVERAGE('Raw Data'!T100:T101) -> 3.5 | U51: =AVERAGE('Raw Data'!U100:U101) -> 3.5 | V51: =AVERAGE('Raw Data'!V100:V101) -> 3 | W51: =AVERAGE('Raw Data'!W100:W101) -> 3 | X51: =AVERAGE('Raw Data'!X100:X101) -> 4 | Y51: =AVERAGE('Raw Data'!Y100:Y101) -> 4 | Z51: =AVERAGE('Raw Data'!Z100:Z101) -> 3.5 | ... AK51: =AVERAGE('Raw Data'!AK100:AK101) -> 2
A52: =A51+1 -> 51 | G52: Brgy. Lunang II Farmers and Fisherfolks Association | S52: =AVERAGE('Raw Data'!S102:S103) -> 4.5 | T52: =AVERAGE('Raw Data'!T102:T103) -> 4.5 | U52: =AVERAGE('Raw Data'!U102:U103) -> 4.5 | V52: =AVERAGE('Raw Data'!V102:V103) -> 3.5 | W52: =AVERAGE('Raw Data'!W102:W103) -> 3 | X52: =AVERAGE('Raw Data'!X102:X103) -> 4 | Y52: =AVERAGE('Raw Data'!Y102:Y103) -> 4 | Z52: =AVERAGE('Raw Data'!Z102:Z103) -> 4 | ... AK52: =AVERAGE('Raw Data'!AK102:AK103) -> 2.5
A53: =A52+1 -> 52 | G53: Barangay Pinalangga Fishermens and Farmers Association | S53: =AVERAGE('Raw Data'!S104:S105) -> 3.5 | T53: =AVERAGE('Raw Data'!T104:T105) -> 3 | U53: =AVERAGE('Raw Data'!U104:U105) -> 3 | V53: =AVERAGE('Raw Data'!V104:V105) -> 3 | W53: =AVERAGE('Raw Data'!W104:W105) -> 3 | X53: =AVERAGE('Raw Data'!X104:X105) -> 4 | Y53: =AVERAGE('Raw Data'!Y104:Y105) -> 3.5 | Z53: =AVERAGE('Raw Data'!Z104:Z105) -> 4.5 | ... AK53: =AVERAGE('Raw Data'!AK104:AK105) -> 2.5
A54: =A53+1 -> 53 | G54: Balocawe Hog Raisers Association | S54: =AVERAGE('Raw Data'!S106:S107) -> 4.5 | T54: =AVERAGE('Raw Data'!T106:T107) -> 3.5 | U54: =AVERAGE('Raw Data'!U106:U107) -> 3.5 | V54: =AVERAGE('Raw Data'!V106:V107) -> 3.5 | W54: =AVERAGE('Raw Data'!W106:W107) -> 3.5 | X54: =AVERAGE('Raw Data'!X106:X107) -> 4 | Y54: =AVERAGE('Raw Data'!Y106:Y107) -> 4 | Z54: =AVERAGE('Raw Data'!Z106:Z107) -> 3.5 | ... AK54: =AVERAGE('Raw Data'!AK106:AK107) -> 1.5
A55: =A54+1 -> 54 | G55: Balogo Integrated Farmers Association | S55: =AVERAGE('Raw Data'!S108:S109) -> 4 | T55: =AVERAGE('Raw Data'!T108:T109) -> 3.5 | U55: =AVERAGE('Raw Data'!U108:U109) -> 4 | V55: =AVERAGE('Raw Data'!V108:V109) -> 3.5 | W55: =AVERAGE('Raw Data'!W108:W109) -> 3.5 | X55: =AVERAGE('Raw Data'!X108:X109) -> 3.5 | Y55: =AVERAGE('Raw Data'!Y108:Y109) -> 4 | Z55: =AVERAGE('Raw Data'!Z108:Z109) -> 4 | ... AK55: =AVERAGE('Raw Data'!AK108:AK109) -> 2
